[
{
  "name": "Alexander",
  "id": "order0",
  "store": "Sprouts Farmers Market",
  "earnings": 20,
  "startingearnings": 20,
  "city": "Oakland",
  "amount": 5,
  "expire": 1,
  "items": {
    "grape": 4,
    "orange": 1
  },
  "demand": 0,
  "generator": "commonsense_item_amount"
},
{
  "name": "Jacob",
  "id": "order1",
  "store": "Sprouts Farmers Market",
  "earnings": 20,
  "startingearnings": 20,
  "city": "Oakland",
  "amount": 15,
  "expire": 1,
  "items": {
    "watermelon": 4,
    "grape": 6,
    "pineapple": 1,
    "apple": 2,
    "kiwi": 2
  },
  "demand": 0,
  "generator": "commonsense_item_amount"
},
{
  "name": "Ava",
  "id": "order2",
  "store": "Sprouts Farmers Market",
  "earnings": 20,
  "startingearnings": 20,
  "city": "Oakland",
  "amount": 15,
  "expire": 1,
  "items": {
    "kiwi": 4,
    "grape": 5,
    "watermelon": 2,
    "apple": 2,
    "orange": 2
  },
  "demand": 0,
  "generator": "commonsense_item_amount"
},
{
  "name": "Isabella",
  "id": "order3",
  "store": "Sprouts Farmers Market",
  "earnings": 20,
  "startingearnings": 20,
  "city": "Oakland",
  "amount": 15,
  "expire": 1,
  "items": {
    "apple": 7,
    "orange": 3,
    "pineapple": 3,
    "grape": 2
  },
  "demand": 0,
  "generator": "commonsense_item_amount"
},
{
  "name": "Charlotte",
  "id": "order4",
  "store": "Safeway",
  "earnings": 20,
  "startingearnings": 20,
  "city": "Piedmont",
  "amount": 10,
  "expire": 1,
  "items": {
    "apple": 4,
    "watermelon": 3,
    "orange": 3
  },
  "demand": 0,
  "generator": "equal_earnings"
},
{
  "name": "Jacob",
  "id": "order5",
  "store": "Target",
  "earnings": 20,
  "startingearnings": 20,
  "city": "Emeryville",
  "amount": 17,
  "expire": 1,
  "items": {
    "pineapple": 2,
    "watermelon": 9,
    "grape": 2,
    "apple": 1,
    "banana": 3
  },
  "demand": 0,
  "generator": "equal_earnings"
},
{
  "name": "James",
  "id": "order6",
  "store": "Safeway",
  "earnings": 20,
  "startingearnings": 20,
  "city": "Piedmont",
  "amount": 11,
  "expire": 1,
  "items": {
    "orange": 4,
    "apple": 3,
    "watermelon": 4
  },
  "demand": 0,
  "generator": "equal_earnings"
},
{
  "name": "William",
  "id": "order7",
  "store": "Target",
  "earnings": 20,
  "startingearnings": 20,
  "city": "Emeryville",
  "amount": 5,
  "expire": 1,
  "items": {
    "banana": 1,
    "apple": 1,
    "pineapple": 1,
    "grape": 1,
    "watermelon": 1
  },
  "demand": 0,
  "generator": "equal_earnings"
},
{
  "name": "Matthew",
  "id": "order8",
  "store": "Sprouts Farmers Market",
  "earnings": 20,
  "startingearnings": 20,
  "city": "Oakland",
  "amount": 11,
  "expire": 1,
  "items": {
    "orange": 3,
    "pear": 1,
    "kiwi": 3,
    "grape": 1,
    "pineapple": 1,
    "apple": 1,
    "watermelon": 1
  },
  "demand": 0,
  "generator": "equal_location_earnings"
},
{
  "name": "Joseph",
  "id": "order9",
  "store": "Sprouts Farmers Market",
  "earnings": 20,
  "startingearnings": 20,
  "city": "Oakland",
  "amount": 18,
  "expire": 1,
  "items": {
    "grape": 2,
    "pineapple": 4,
    "orange": 2,
    "apple": 2,
    "kiwi": 2,
    "pear": 6
  },
  "demand": 0,
  "generator": "equal_location_earnings"
},
{
  "name": "Lucas",
  "id": "order10",
  "store": "Sprouts Farmers Market",
  "earnings": 20,
  "startingearnings": 20,
  "city": "Oakland",
  "amount": 7,
  "expire": 1,
  "items": {
    "grape": 2,
    "orange": 1,
    "watermelon": 2,
    "apple": 1,
    "kiwi": 1
  },
  "demand": 0,
  "generator": "equal_location_earnings"
},
{
  "name": "Joseph",
  "id": "order11",
  "store": "Sprouts Farmers Market",
  "earnings": 20,
  "startingearnings": 20,
  "city": "Oakland",
  "amount": 6,
  "expire": 1,
  "items": {
    "apple": 1,
    "pineapple": 1,
    "kiwi": 1,
    "orange": 1,
    "grape": 2
  },
  "demand": 0,
  "generator": "equal_location_earnings"
},
{
  "name": "Christopher",
  "id": "order12",
  "store": "Sprouts Farmers Market",
  "earnings": 20,
  "startingearnings": 20,
  "city": "Oakland",
  "amount": 9,
  "expire": 1,
  "items": {
    "watermelon": 1,
    "kiwi": 2,
    "apple": 1,
    "grape": 2,
    "pear": 2,
    "orange": 1
  },
  "demand": 0,
  "generator": "equal_location_earnings"
},
{
  "name": "Noah",
  "id": "order13",
  "store": "Sprouts Farmers Market",
  "earnings": 20,
  "startingearnings": 20,
  "city": "Oakland",
  "amount": 15,
  "expire": 1,
  "items": {
    "orange": 2,
    "apple": 4,
    "kiwi": 4,
    "pineapple": 2,
    "watermelon": 2,
    "pear": 1
  },
  "demand": 0,
  "generator": "equal_location_earnings"
},
{
  "name": "Mason",
  "id": "order14",
  "store": "Sprouts Farmers Market",
  "earnings": 20,
  "startingearnings": 20,
  "city": "Oakland",
  "amount": 13,
  "expire": 1,
  "items": {
    "watermelon": 5,
    "apple": 2,
    "pineapple": 1,
    "grape": 1,
    "kiwi": 1,
    "pear": 2,
    "orange": 1
  },
  "demand": 0,
  "generator": "equal_location_earnings"
},
{
  "name": "Evelyn",
  "id": "order15",
  "store": "Sprouts Farmers Market",
  "earnings": 20,
  "startingearnings": 20,
  "city": "Oakland",
  "amount": 1,
  "expire": 1,
  "items": {
    "orange": 1
  },
  "demand": 0,
  "generator": "equal_location_earnings"
},
{
  "name": "Abigail",
  "id": "order16",
  "store": "Berkeley Bowl",
  "earnings": 39,
  "startingearnings": 39,
  "city": "Berkeley",
  "amount": 11,
  "expire": 1,
  "items": {
    "orange": 2,
    "apple": 3,
    "grape": 4,
    "pineapple": 2
  },
  "demand": 0,
  "generator": "pure_randomness"
},
{
  "name": "Emma",
  "id": "order17",
  "store": "Safeway",
  "earnings": 37,
  "startingearnings": 37,
  "city": "Piedmont",
  "amount": 18,
  "expire": 1,
  "items": {
    "orange": 9,
    "apple": 4,
    "watermelon": 5
  },
  "demand": 0,
  "generator": "pure_randomness"
},
{
  "name": "Elijah",
  "id": "order18",
  "store": "Safeway",
  "earnings": 13,
  "startingearnings": 13,
  "city": "Piedmont",
  "amount": 19,
  "expire": 1,
  "items": {
    "apple": 7,
    "orange": 10,
    "watermelon": 2
  },
  "demand": 0,
  "generator": "pure_randomness"
},
{
  "name": "Oliver",
  "id": "order19",
  "store": "Target",
  "earnings": 32,
  "startingearnings": 32,
  "city": "Emeryville",
  "amount": 19,
  "expire": 1,
  "items": {
    "grape": 7,
    "watermelon": 2,
    "apple": 6,
    "pineapple": 2,
    "banana": 2
  },
  "demand": 0,
  "generator": "pure_randomness"
},
{
  "name": "Amelia",
  "id": "order16",
  "store": "Safeway",
  "earnings": 20,
  "startingearnings": 20,
  "city": "Piedmont",
  "amount": 8,
  "expire": 1,
  "items": {
    "apple": 3,
    "orange": 5
  },
  "demand": 0,
  "generator": "vary_location"
},
{
  "name": "Liam",
  "id": "order17",
  "store": "Berkeley Bowl",
  "earnings": 20,
  "startingearnings": 20,
  "city": "Berkeley",
  "amount": 8,
  "expire": 1,
  "items": {
    "grape": 7,
    "orange": 1
  },
  "demand": 0,
  "generator": "vary_location"
},
{
  "name": "Ethan",
  "id": "order18",
  "store": "Berkeley Bowl",
  "earnings": 20,
  "startingearnings": 20,
  "city": "Berkeley",
  "amount": 8,
  "expire": 1,
  "items": {
    "watermelon": 6,
    "pineapple": 2
  },
  "demand": 0,
  "generator": "vary_location"
},
{
  "name": "Emma",
  "id": "order19",
  "store": "Berkeley Bowl",
  "earnings": 20,
  "startingearnings": 20,
  "city": "Berkeley",
  "amount": 8,
  "expire": 1,
  "items": {
    "watermelon": 5,
    "apple": 3
  },
  "demand": 0,
  "generator": "vary_location"
},
{
  "name": "Joseph",
  "id": "order20",
  "store": "Sprouts Farmers Market",
  "earnings": 20,
  "startingearnings": 20,
  "city": "Oakland",
  "amount": 2,
  "expire": 1,
  "items": {
    "kiwi": 1,
    "pineapple": 1
  },
  "demand": 0,
  "generator": "equal_location_earnings"
},
{
  "name": "William",
  "id": "order21",
  "store": "Sprouts Farmers Market",
  "earnings": 20,
  "startingearnings": 20,
  "city": "Oakland",
  "amount": 10,
  "expire": 1,
  "items": {
    "watermelon": 2,
    "orange": 3,
    "kiwi": 1,
    "grape": 1,
    "pear": 2,
    "pineapple": 1
  },
  "demand": 0,
  "generator": "equal_location_earnings"
},
{
  "name": "Elijah",
  "id": "order22",
  "store": "Sprouts Farmers Market",
  "earnings": 20,
  "startingearnings": 20,
  "city": "Oakland",
  "amount": 1,
  "expire": 1,
  "items": {
    "apple": 1
  },
  "demand": 0,
  "generator": "equal_location_earnings"
},
{
  "name": "Lucas",
  "id": "order23",
  "store": "Sprouts Farmers Market",
  "earnings": 20,
  "startingearnings": 20,
  "city": "Oakland",
  "amount": 19,
  "expire": 1,
  "items": {
    "pineapple": 2,
    "pear": 4,
    "orange": 4,
    "grape": 1,
    "apple": 4,
    "kiwi": 3,
    "watermelon": 1
  },
  "demand": 0,
  "generator": "equal_location_earnings"
},
{
  "name": "Noah",
  "id": "order24",
  "store": "Sprouts Farmers Market",
  "earnings": 20,
  "startingearnings": 20,
  "city": "Oakland",
  "amount": 5,
  "expire": 1,
  "items": {
    "grape": 3,
    "pineapple": 2
  },
  "demand": 0,
  "generator": "commonsense_item_amount"
},
{
  "name": "Joseph",
  "id": "order25",
  "store": "Sprouts Farmers Market",
  "earnings": 20,
  "startingearnings": 20,
  "city": "Oakland",
  "amount": 15,
  "expire": 1,
  "items": {
    "kiwi": 6,
    "orange": 1,
    "pear": 4,
    "grape": 2,
    "apple": 2
  },
  "demand": 0,
  "generator": "commonsense_item_amount"
},
{
  "name": "Emma",
  "id": "order26",
  "store": "Sprouts Farmers Market",
  "earnings": 20,
  "startingearnings": 20,
  "city": "Oakland",
  "amount": 15,
  "expire": 1,
  "items": {
    "kiwi": 5,
    "orange": 4,
    "watermelon": 2,
    "pear": 3,
    "grape": 1
  },
  "demand": 0,
  "generator": "commonsense_item_amount"
},
{
  "name": "Lucas",
  "id": "order27",
  "store": "Sprouts Farmers Market",
  "earnings": 20,
  "startingearnings": 20,
  "city": "Oakland",
  "amount": 15,
  "expire": 1,
  "items": {
    "apple": 2,
    "pineapple": 5,
    "kiwi": 3,
    "pear": 4,
    "watermelon": 1
  },
  "demand": 0,
  "generator": "commonsense_item_amount"
},
{
  "name": "Ava",
  "id": "order28",
  "store": "Sprouts Farmers Market",
  "earnings": 20,
  "startingearnings": 20,
  "city": "Oakland",
  "amount": 19,
  "expire": 1,
  "items": {
    "watermelon": 5,
    "apple": 1,
    "kiwi": 1,
    "grape": 6,
    "pear": 4,
    "orange": 2
  },
  "demand": 0,
  "generator": "equal_location_earnings"
},
{
  "name": "Lucas",
  "id": "order29",
  "store": "Sprouts Farmers Market",
  "earnings": 20,
  "startingearnings": 20,
  "city": "Oakland",
  "amount": 19,
  "expire": 1,
  "items": {
    "pineapple": 3,
    "grape": 2,
    "kiwi": 5,
    "orange": 5,
    "apple": 2,
    "watermelon": 1,
    "pear": 1
  },
  "demand": 0,
  "generator": "equal_location_earnings"
},
{
  "name": "Ava",
  "id": "order30",
  "store": "Sprouts Farmers Market",
  "earnings": 20,
  "startingearnings": 20,
  "city": "Oakland",
  "amount": 7,
  "expire": 1,
  "items": {
    "grape": 3,
    "pineapple": 1,
    "apple": 1,
    "watermelon": 2
  },
  "demand": 0,
  "generator": "equal_location_earnings"
},
{
  "name": "Michael",
  "id": "order31",
  "store": "Sprouts Farmers Market",
  "earnings": 20,
  "startingearnings": 20,
  "city": "Oakland",
  "amount": 2,
  "expire": 1,
  "items": {
    "kiwi": 2
  },
  "demand": 0,
  "generator": "equal_location_earnings"
},
{
  "name": "Lucas",
  "id": "order32",
  "store": "Berkeley Bowl",
  "earnings": 22,
  "startingearnings": 22,
  "city": "Berkeley",
  "amount": 1,
  "expire": 1,
  "items": {
    "grape": 1
  },
  "demand": 0,
  "generator": "pure_randomness"
},
{
  "name": "Mason",
  "id": "order33",
  "store": "Berkeley Bowl",
  "earnings": 14,
  "startingearnings": 14,
  "city": "Berkeley",
  "amount": 1,
  "expire": 1,
  "items": {
    "orange": 1
  },
  "demand": 0,
  "generator": "pure_randomness"
},
{
  "name": "Mia",
  "id": "order34",
  "store": "Berkeley Bowl",
  "earnings": 21,
  "startingearnings": 21,
  "city": "Berkeley",
  "amount": 1,
  "expire": 1,
  "items": {
    "grape": 1
  },
  "demand": 0,
  "generator": "pure_randomness"
},
{
  "name": "David",
  "id": "order35",
  "store": "Safeway",
  "earnings": 39,
  "startingearnings": 39,
  "city": "Piedmont",
  "amount": 6,
  "expire": 1,
  "items": {
    "orange": 2,
    "apple": 2,
    "watermelon": 2
  },
  "demand": 0,
  "generator": "pure_randomness"
},
{
  "name": "Matthew",
  "id": "order32",
  "store": "Sprouts Farmers Market",
  "earnings": 20,
  "startingearnings": 20,
  "city": "Oakland",
  "amount": 8,
  "expire": 1,
  "items": {
    "orange": 4,
    "watermelon": 4
  },
  "demand": 0,
  "generator": "vary_location"
},
{
  "name": "Charlotte",
  "id": "order33",
  "store": "Sprouts Farmers Market",
  "earnings": 20,
  "startingearnings": 20,
  "city": "Oakland",
  "amount": 8,
  "expire": 1,
  "items": {
    "pineapple": 6,
    "grape": 2
  },
  "demand": 0,
  "generator": "vary_location"
},
{
  "name": "Ava",
  "id": "order34",
  "store": "Safeway",
  "earnings": 20,
  "startingearnings": 20,
  "city": "Piedmont",
  "amount": 8,
  "expire": 1,
  "items": {
    "apple": 4,
    "watermelon": 4
  },
  "demand": 0,
  "generator": "vary_location"
},
{
  "name": "Park",
  "id": "order35",
  "store": "Berkeley Bowl",
  "earnings": 20,
  "startingearnings": 20,
  "city": "Berkeley",
  "amount": 8,
  "expire": 1,
  "items": {
    "watermelon": 6,
    "pineapple": 2
  },
  "demand": 0,
  "generator": "vary_location"
},
{
  "name": "Benjamin",
  "id": "order36",
  "store": "Sprouts Farmers Market",
  "earnings": 20,
  "startingearnings": 20,
  "city": "Oakland",
  "amount": 6,
  "expire": 1,
  "items": {
    "watermelon": 3,
    "pineapple": 2,
    "grape": 1
  },
  "demand": 0,
  "generator": "equal_everything"
},
{
  "name": "Benjamin",
  "id": "order37",
  "store": "Sprouts Farmers Market",
  "earnings": 20,
  "startingearnings": 20,
  "city": "Oakland",
  "amount": 6,
  "expire": 1,
  "items": {
    "watermelon": 2,
    "pineapple": 3,
    "apple": 1
  },
  "demand": 0,
  "generator": "equal_everything"
},
{
  "name": "Ethan",
  "id": "order38",
  "store": "Sprouts Farmers Market",
  "earnings": 20,
  "startingearnings": 20,
  "city": "Oakland",
  "amount": 6,
  "expire": 1,
  "items": {
    "pear": 3,
    "watermelon": 2,
    "apple": 1
  },
  "demand": 0,
  "generator": "equal_everything"
},
{
  "name": "William",
  "id": "order39",
  "store": "Sprouts Farmers Market",
  "earnings": 20,
  "startingearnings": 20,
  "city": "Oakland",
  "amount": 6,
  "expire": 1,
  "items": {
    "kiwi": 4,
    "apple": 2
  },
  "demand": 0,
  "generator": "equal_everything"
},
{
  "name": "Ethan",
  "id": "order40",
  "store": "Sprouts Farmers Market",
  "earnings": 20,
  "startingearnings": 20,
  "city": "Oakland",
  "amount": 16,
  "expire": 1,
  "items": {
    "pineapple": 1,
    "kiwi": 3,
    "watermelon": 4,
    "grape": 4,
    "orange": 2,
    "pear": 1,
    "apple": 1
  },
  "demand": 0,
  "generator": "equal_location_earnings"
},
{
  "name": "Oliver",
  "id": "order41",
  "store": "Sprouts Farmers Market",
  "earnings": 20,
  "startingearnings": 20,
  "city": "Oakland",
  "amount": 1,
  "expire": 1,
  "items": {
    "pear": 1
  },
  "demand": 0,
  "generator": "equal_location_earnings"
},
{
  "name": "Marcus",
  "id": "order42",
  "store": "Sprouts Farmers Market",
  "earnings": 20,
  "startingearnings": 20,
  "city": "Oakland",
  "amount": 7,
  "expire": 1,
  "items": {
    "pear": 1,
    "kiwi": 1,
    "pineapple": 1,
    "watermelon": 2,
    "apple": 2
  },
  "demand": 0,
  "generator": "equal_location_earnings"
},
{
  "name": "Abigail",
  "id": "order43",
  "store": "Sprouts Farmers Market",
  "earnings": 20,
  "startingearnings": 20,
  "city": "Oakland",
  "amount": 6,
  "expire": 1,
  "items": {
    "kiwi": 1,
    "pineapple": 2,
    "apple": 2,
    "grape": 1
  },
  "demand": 0,
  "generator": "equal_location_earnings"
},
{
  "name": "Sophia",
  "id": "order44",
  "store": "Sprouts Farmers Market",
  "earnings": 20,
  "startingearnings": 20,
  "city": "Oakland",
  "amount": 3,
  "expire": 1,
  "items": {
    "apple": 1,
    "pear": 1,
    "kiwi": 1
  },
  "demand": 0,
  "generator": "equal_location_earnings"
},
{
  "name": "Daniel",
  "id": "order45",
  "store": "Sprouts Farmers Market",
  "earnings": 20,
  "startingearnings": 20,
  "city": "Oakland",
  "amount": 12,
  "expire": 1,
  "items": {
    "pineapple": 2,
    "kiwi": 4,
    "orange": 2,
    "grape": 2,
    "watermelon": 1,
    "pear": 1
  },
  "demand": 0,
  "generator": "equal_location_earnings"
},
{
  "name": "Michael",
  "id": "order46",
  "store": "Sprouts Farmers Market",
  "earnings": 20,
  "startingearnings": 20,
  "city": "Oakland",
  "amount": 19,
  "expire": 1,
  "items": {
    "kiwi": 5,
    "pineapple": 3,
    "pear": 5,
    "apple": 1,
    "orange": 1,
    "grape": 3,
    "watermelon": 1
  },
  "demand": 0,
  "generator": "equal_location_earnings"
},
{
  "name": "Michael",
  "id": "order47",
  "store": "Sprouts Farmers Market",
  "earnings": 20,
  "startingearnings": 20,
  "city": "Oakland",
  "amount": 19,
  "expire": 1,
  "items": {
    "apple": 3,
    "pear": 4,
    "pineapple": 3,
    "grape": 1,
    "orange": 2,
    "watermelon": 5,
    "kiwi": 1
  },
  "demand": 0,
  "generator": "equal_location_earnings"
},
{
  "name": "Noah",
  "id": "order48",
  "store": "Target",
  "earnings": 14,
  "startingearnings": 14,
  "city": "Emeryville",
  "amount": 6,
  "expire": 1,
  "items": {
    "watermelon": 1,
    "banana": 2,
    "grape": 1,
    "apple": 1,
    "pineapple": 1
  },
  "demand": 0,
  "generator": "pure_randomness"
},
{
  "name": "Aiden",
  "id": "order49",
  "store": "Safeway",
  "earnings": 33,
  "startingearnings": 33,
  "city": "Piedmont",
  "amount": 11,
  "expire": 1,
  "items": {
    "watermelon": 7,
    "apple": 3,
    "orange": 1
  },
  "demand": 0,
  "generator": "pure_randomness"
},
{
  "name": "David",
  "id": "order50",
  "store": "Berkeley Bowl",
  "earnings": 6,
  "startingearnings": 6,
  "city": "Berkeley",
  "amount": 11,
  "expire": 1,
  "items": {
    "grape": 2,
    "apple": 5,
    "pineapple": 2,
    "orange": 1,
    "watermelon": 1
  },
  "demand": 0,
  "generator": "pure_randomness"
},
{
  "name": "Amelia",
  "id": "order51",
  "store": "Safeway",
  "earnings": 17,
  "startingearnings": 17,
  "city": "Piedmont",
  "amount": 10,
  "expire": 1,
  "items": {
    "orange": 4,
    "apple": 3,
    "watermelon": 3
  },
  "demand": 0,
  "generator": "pure_randomness"
},
{
  "name": "James",
  "id": "order48",
  "store": "Sprouts Farmers Market",
  "earnings": 20,
  "startingearnings": 20,
  "city": "Oakland",
  "amount": 2,
  "expire": 1,
  "items": {
    "grape": 2
  },
  "demand": 0,
  "generator": "equal_location_earnings"
},
{
  "name": "James",
  "id": "order49",
  "store": "Sprouts Farmers Market",
  "earnings": 20,
  "startingearnings": 20,
  "city": "Oakland",
  "amount": 9,
  "expire": 1,
  "items": {
    "apple": 1,
    "grape": 1,
    "orange": 2,
    "pineapple": 2,
    "pear": 1,
    "kiwi": 1,
    "watermelon": 1
  },
  "demand": 0,
  "generator": "equal_location_earnings"
},
{
  "name": "Ethan",
  "id": "order50",
  "store": "Sprouts Farmers Market",
  "earnings": 20,
  "startingearnings": 20,
  "city": "Oakland",
  "amount": 11,
  "expire": 1,
  "items": {
    "watermelon": 5,
    "pear": 2,
    "apple": 1,
    "pineapple": 2,
    "kiwi": 1
  },
  "demand": 0,
  "generator": "equal_location_earnings"
},
{
  "name": "Ethan",
  "id": "order51",
  "store": "Sprouts Farmers Market",
  "earnings": 20,
  "startingearnings": 20,
  "city": "Oakland",
  "amount": 1,
  "expire": 1,
  "items": {
    "orange": 1
  },
  "demand": 0,
  "generator": "equal_location_earnings"
},
{
  "name": "Isabella",
  "id": "order52",
  "store": "Sprouts Farmers Market",
  "earnings": 20,
  "startingearnings": 20,
  "city": "Oakland",
  "amount": 15,
  "expire": 1,
  "items": {
    "pear": 3,
    "grape": 3,
    "pineapple": 4,
    "apple": 5
  },
  "demand": 0,
  "generator": "commonsense_item_amount"
},
{
  "name": "Olivia",
  "id": "order53",
  "store": "Sprouts Farmers Market",
  "earnings": 20,
  "startingearnings": 20,
  "city": "Oakland",
  "amount": 15,
  "expire": 1,
  "items": {
    "watermelon": 2,
    "kiwi": 5,
    "grape": 1,
    "pear": 4,
    "orange": 3
  },
  "demand": 0,
  "generator": "commonsense_item_amount"
},
{
  "name": "Matthew",
  "id": "order54",
  "store": "Sprouts Farmers Market",
  "earnings": 20,
  "startingearnings": 20,
  "city": "Oakland",
  "amount": 15,
  "expire": 1,
  "items": {
    "orange": 2,
    "watermelon": 5,
    "kiwi": 4,
    "pear": 3,
    "apple": 1
  },
  "demand": 0,
  "generator": "commonsense_item_amount"
},
{
  "name": "Aiden",
  "id": "order55",
  "store": "Sprouts Farmers Market",
  "earnings": 20,
  "startingearnings": 20,
  "city": "Oakland",
  "amount": 5,
  "expire": 1,
  "items": {
    "watermelon": 3,
    "apple": 2
  },
  "demand": 0,
  "generator": "commonsense_item_amount"
},
{
  "name": "Logan",
  "id": "order56",
  "store": "Sprouts Farmers Market",
  "earnings": 20,
  "startingearnings": 20,
  "city": "Oakland",
  "amount": 6,
  "expire": 1,
  "items": {
    "grape": 3,
    "apple": 2,
    "kiwi": 1
  },
  "demand": 0,
  "generator": "equal_everything"
},
{
  "name": "Mason",
  "id": "order57",
  "store": "Sprouts Farmers Market",
  "earnings": 20,
  "startingearnings": 20,
  "city": "Oakland",
  "amount": 6,
  "expire": 1,
  "items": {
    "kiwi": 4,
    "apple": 1,
    "orange": 1
  },
  "demand": 0,
  "generator": "equal_everything"
},
{
  "name": "Sophia",
  "id": "order58",
  "store": "Sprouts Farmers Market",
  "earnings": 20,
  "startingearnings": 20,
  "city": "Oakland",
  "amount": 6,
  "expire": 1,
  "items": {
    "grape": 3,
    "pear": 2,
    "orange": 1
  },
  "demand": 0,
  "generator": "equal_everything"
},
{
  "name": "James",
  "id": "order59",
  "store": "Sprouts Farmers Market",
  "earnings": 20,
  "startingearnings": 20,
  "city": "Oakland",
  "amount": 6,
  "expire": 1,
  "items": {
    "orange": 4,
    "pineapple": 1,
    "watermelon": 1
  },
  "demand": 0,
  "generator": "equal_everything"
},
{
  "name": "Ethan",
  "id": "order60",
  "store": "Sprouts Farmers Market",
  "earnings": 20,
  "startingearnings": 20,
  "city": "Oakland",
  "amount": 4,
  "expire": 1,
  "items": {
    "pear": 1,
    "kiwi": 1,
    "grape": 1,
    "watermelon": 1
  },
  "demand": 0,
  "generator": "equal_location_earnings"
},
{
  "name": "Sophia",
  "id": "order61",
  "store": "Sprouts Farmers Market",
  "earnings": 20,
  "startingearnings": 20,
  "city": "Oakland",
  "amount": 12,
  "expire": 1,
  "items": {
    "orange": 3,
    "watermelon": 3,
    "pear": 2,
    "kiwi": 1,
    "grape": 1,
    "apple": 2
  },
  "demand": 0,
  "generator": "equal_location_earnings"
},
{
  "name": "James",
  "id": "order62",
  "store": "Sprouts Farmers Market",
  "earnings": 20,
  "startingearnings": 20,
  "city": "Oakland",
  "amount": 4,
  "expire": 1,
  "items": {
    "pineapple": 1,
    "pear": 1,
    "grape": 1,
    "orange": 1
  },
  "demand": 0,
  "generator": "equal_location_earnings"
},
{
  "name": "Emma",
  "id": "order63",
  "store": "Sprouts Farmers Market",
  "earnings": 20,
  "startingearnings": 20,
  "city": "Oakland",
  "amount": 9,
  "expire": 1,
  "items": {
    "kiwi": 1,
    "grape": 2,
    "pineapple": 2,
    "pear": 1,
    "watermelon": 1,
    "orange": 1,
    "apple": 1
  },
  "demand": 0,
  "generator": "equal_location_earnings"
},
{
  "name": "Benjamin",
  "id": "order64",
  "store": "Berkeley Bowl",
  "earnings": 34,
  "startingearnings": 34,
  "city": "Berkeley",
  "amount": 9,
  "expire": 1,
  "items": {
    "pineapple": 2,
    "watermelon": 3,
    "apple": 2,
    "grape": 1,
    "orange": 1
  },
  "demand": 0,
  "generator": "pure_randomness"
},
{
  "name": "Ava",
  "id": "order65",
  "store": "Target",
  "earnings": 32,
  "startingearnings": 32,
  "city": "Emeryville",
  "amount": 3,
  "expire": 1,
  "items": {
    "grape": 1,
    "banana": 2
  },
  "demand": 0,
  "generator": "pure_randomness"
},
{
  "name": "David",
  "id": "order66",
  "store": "Berkeley Bowl",
  "earnings": 21,
  "startingearnings": 21,
  "city": "Berkeley",
  "amount": 18,
  "expire": 1,
  "items": {
    "pineapple": 4,
    "grape": 2,
    "apple": 2,
    "watermelon": 5,
    "orange": 5
  },
  "demand": 0,
  "generator": "pure_randomness"
},
{
  "name": "Oliver",
  "id": "order67",
  "store": "Sprouts Farmers Market",
  "earnings": 9,
  "startingearnings": 9,
  "city": "Oakland",
  "amount": 8,
  "expire": 1,
  "items": {
    "grape": 2,
    "watermelon": 2,
    "pineapple": 2,
    "pear": 1,
    "apple": 1
  },
  "demand": 0,
  "generator": "pure_randomness"
},
{
  "name": "Christopher",
  "id": "order64",
  "store": "Sprouts Farmers Market",
  "earnings": 20,
  "startingearnings": 20,
  "city": "Oakland",
  "amount": 8,
  "expire": 1,
  "items": {
    "grape": 4,
    "pear": 4
  },
  "demand": 0,
  "generator": "vary_location"
},
{
  "name": "Elijah",
  "id": "order65",
  "store": "Sprouts Farmers Market",
  "earnings": 20,
  "startingearnings": 20,
  "city": "Oakland",
  "amount": 8,
  "expire": 1,
  "items": {
    "pear": 5,
    "apple": 3
  },
  "demand": 0,
  "generator": "vary_location"
},
{
  "name": "Logan",
  "id": "order66",
  "store": "Safeway",
  "earnings": 20,
  "startingearnings": 20,
  "city": "Piedmont",
  "amount": 8,
  "expire": 1,
  "items": {
    "orange": 5,
    "watermelon": 3
  },
  "demand": 0,
  "generator": "vary_location"
},
{
  "name": "Logan",
  "id": "order67",
  "store": "Safeway",
  "earnings": 20,
  "startingearnings": 20,
  "city": "Piedmont",
  "amount": 8,
  "expire": 1,
  "items": {
    "watermelon": 8
  },
  "demand": 0,
  "generator": "vary_location"
},
{
  "name": "Alexander",
  "id": "order68",
  "store": "Sprouts Farmers Market",
  "earnings": 20,
  "startingearnings": 20,
  "city": "Oakland",
  "amount": 6,
  "expire": 1,
  "items": {
    "kiwi": 2,
    "orange": 1,
    "grape": 1,
    "pineapple": 1,
    "apple": 1
  },
  "demand": 0,
  "generator": "equal_location_earnings"
},
{
  "name": "Alexander",
  "id": "order69",
  "store": "Sprouts Farmers Market",
  "earnings": 20,
  "startingearnings": 20,
  "city": "Oakland",
  "amount": 2,
  "expire": 1,
  "items": {
    "pear": 1,
    "pineapple": 1
  },
  "demand": 0,
  "generator": "equal_location_earnings"
},
{
  "name": "Alexander",
  "id": "order70",
  "store": "Sprouts Farmers Market",
  "earnings": 20,
  "startingearnings": 20,
  "city": "Oakland",
  "amount": 4,
  "expire": 1,
  "items": {
    "kiwi": 1,
    "watermelon": 1,
    "pineapple": 1,
    "apple": 1
  },
  "demand": 0,
  "generator": "equal_location_earnings"
},
{
  "name": "Lucas",
  "id": "order71",
  "store": "Sprouts Farmers Market",
  "earnings": 20,
  "startingearnings": 20,
  "city": "Oakland",
  "amount": 5,
  "expire": 1,
  "items": {
    "pear": 1,
    "grape": 1,
    "pineapple": 1,
    "orange": 1,
    "watermelon": 1
  },
  "demand": 0,
  "generator": "equal_location_earnings"
},
{
  "name": "David",
  "id": "order72",
  "store": "Sprouts Farmers Market",
  "earnings": 25,
  "startingearnings": 25,
  "city": "Oakland",
  "amount": 17,
  "expire": 1,
  "items": {
    "pineapple": 3,
    "grape": 8,
    "kiwi": 3,
    "watermelon": 2,
    "apple": 1
  },
  "demand": 0,
  "generator": "pure_randomness"
},
{
  "name": "James",
  "id": "order73",
  "store": "Berkeley Bowl",
  "earnings": 39,
  "startingearnings": 39,
  "city": "Berkeley",
  "amount": 18,
  "expire": 1,
  "items": {
    "orange": 6,
    "apple": 4,
    "pineapple": 2,
    "watermelon": 4,
    "grape": 2
  },
  "demand": 0,
  "generator": "pure_randomness"
},
{
  "name": "Noah",
  "id": "order74",
  "store": "Berkeley Bowl",
  "earnings": 32,
  "startingearnings": 32,
  "city": "Berkeley",
  "amount": 3,
  "expire": 1,
  "items": {
    "grape": 1,
    "orange": 1,
    "apple": 1
  },
  "demand": 0,
  "generator": "pure_randomness"
},
{
  "name": "Charlotte",
  "id": "order75",
  "store": "Sprouts Farmers Market",
  "earnings": 23,
  "startingearnings": 23,
  "city": "Oakland",
  "amount": 12,
  "expire": 1,
  "items": {
    "watermelon": 1,
    "pear": 1,
    "grape": 2,
    "kiwi": 1,
    "apple": 3,
    "orange": 1,
    "pineapple": 3
  },
  "demand": 0,
  "generator": "pure_randomness"
},
{
  "name": "Mia",
  "id": "order76",
  "store": "Sprouts Farmers Market",
  "earnings": 20,
  "startingearnings": 20,
  "city": "Oakland",
  "amount": 6,
  "expire": 1,
  "items": {
    "kiwi": 2,
    "pineapple": 1,
    "apple": 3
  },
  "demand": 0,
  "generator": "equal_everything"
},
{
  "name": "Mason",
  "id": "order77",
  "store": "Sprouts Farmers Market",
  "earnings": 20,
  "startingearnings": 20,
  "city": "Oakland",
  "amount": 6,
  "expire": 1,
  "items": {
    "apple": 1,
    "watermelon": 2,
    "grape": 3
  },
  "demand": 0,
  "generator": "equal_everything"
},
{
  "name": "Charlotte",
  "id": "order78",
  "store": "Sprouts Farmers Market",
  "earnings": 20,
  "startingearnings": 20,
  "city": "Oakland",
  "amount": 6,
  "expire": 1,
  "items": {
    "orange": 2,
    "apple": 3,
    "pear": 1
  },
  "demand": 0,
  "generator": "equal_everything"
},
{
  "name": "Liam",
  "id": "order79",
  "store": "Sprouts Farmers Market",
  "earnings": 20,
  "startingearnings": 20,
  "city": "Oakland",
  "amount": 6,
  "expire": 1,
  "items": {
    "apple": 1,
    "pear": 4,
    "grape": 1
  },
  "demand": 0,
  "generator": "equal_everything"
},
{
  "name": "Mia",
  "id": "order80",
  "store": "Target",
  "earnings": 27,
  "startingearnings": 27,
  "city": "Emeryville",
  "amount": 9,
  "expire": 1,
  "items": {
    "grape": 3,
    "banana": 3,
    "pineapple": 1,
    "apple": 1,
    "watermelon": 1
  },
  "demand": 0,
  "generator": "pure_randomness"
},
{
  "name": "Emma",
  "id": "order81",
  "store": "Sprouts Farmers Market",
  "earnings": 11,
  "startingearnings": 11,
  "city": "Oakland",
  "amount": 9,
  "expire": 1,
  "items": {
    "kiwi": 3,
    "apple": 2,
    "grape": 2,
    "pineapple": 2
  },
  "demand": 0,
  "generator": "pure_randomness"
},
{
  "name": "Elijah",
  "id": "order82",
  "store": "Sprouts Farmers Market",
  "earnings": 26,
  "startingearnings": 26,
  "city": "Oakland",
  "amount": 17,
  "expire": 1,
  "items": {
    "pear": 3,
    "watermelon": 4,
    "pineapple": 3,
    "apple": 2,
    "grape": 3,
    "orange": 1,
    "kiwi": 1
  },
  "demand": 0,
  "generator": "pure_randomness"
},
{
  "name": "Benjamin",
  "id": "order83",
  "store": "Safeway",
  "earnings": 10,
  "startingearnings": 10,
  "city": "Piedmont",
  "amount": 13,
  "expire": 1,
  "items": {
    "orange": 6,
    "apple": 5,
    "watermelon": 2
  },
  "demand": 0,
  "generator": "pure_randomness"
},
{
  "name": "Ava",
  "id": "order80",
  "store": "Berkeley Bowl",
  "earnings": 20,
  "startingearnings": 20,
  "city": "Berkeley",
  "amount": 8,
  "expire": 1,
  "items": {
    "apple": 4,
    "watermelon": 4
  },
  "demand": 0,
  "generator": "vary_location"
},
{
  "name": "Lucas",
  "id": "order81",
  "store": "Target",
  "earnings": 20,
  "startingearnings": 20,
  "city": "Emeryville",
  "amount": 8,
  "expire": 1,
  "items": {
    "banana": 2,
    "pineapple": 6
  },
  "demand": 0,
  "generator": "vary_location"
},
{
  "name": "Oliver",
  "id": "order82",
  "store": "Sprouts Farmers Market",
  "earnings": 20,
  "startingearnings": 20,
  "city": "Oakland",
  "amount": 8,
  "expire": 1,
  "items": {
    "watermelon": 3,
    "kiwi": 5
  },
  "demand": 0,
  "generator": "vary_location"
},
{
  "name": "Michael",
  "id": "order83",
  "store": "Safeway",
  "earnings": 20,
  "startingearnings": 20,
  "city": "Piedmont",
  "amount": 8,
  "expire": 1,
  "items": {
    "orange": 4,
    "apple": 4
  },
  "demand": 0,
  "generator": "vary_location"
},
{
  "name": "Mason",
  "id": "order84",
  "store": "Sprouts Farmers Market",
  "earnings": 20,
  "startingearnings": 20,
  "city": "Oakland",
  "amount": 3,
  "expire": 1,
  "items": {
    "kiwi": 2,
    "watermelon": 1
  },
  "demand": 0,
  "generator": "equal_location_earnings"
},
{
  "name": "Ava",
  "id": "order85",
  "store": "Sprouts Farmers Market",
  "earnings": 20,
  "startingearnings": 20,
  "city": "Oakland",
  "amount": 19,
  "expire": 1,
  "items": {
    "pear": 4,
    "kiwi": 3,
    "orange": 2,
    "watermelon": 4,
    "pineapple": 2,
    "grape": 3,
    "apple": 1
  },
  "demand": 0,
  "generator": "equal_location_earnings"
},
{
  "name": "Mia",
  "id": "order86",
  "store": "Sprouts Farmers Market",
  "earnings": 20,
  "startingearnings": 20,
  "city": "Oakland",
  "amount": 6,
  "expire": 1,
  "items": {
    "pineapple": 1,
    "apple": 2,
    "orange": 1,
    "watermelon": 2
  },
  "demand": 0,
  "generator": "equal_location_earnings"
},
{
  "name": "Elijah",
  "id": "order87",
  "store": "Sprouts Farmers Market",
  "earnings": 20,
  "startingearnings": 20,
  "city": "Oakland",
  "amount": 18,
  "expire": 1,
  "items": {
    "watermelon": 5,
    "pear": 4,
    "orange": 2,
    "apple": 2,
    "kiwi": 3,
    "pineapple": 2
  },
  "demand": 0,
  "generator": "equal_location_earnings"
},
{
  "name": "Amelia",
  "id": "order88",
  "store": "Sprouts Farmers Market",
  "earnings": 20,
  "startingearnings": 20,
  "city": "Oakland",
  "amount": 11,
  "expire": 1,
  "items": {
    "grape": 1,
    "pineapple": 1,
    "pear": 3,
    "apple": 1,
    "watermelon": 1,
    "orange": 4
  },
  "demand": 0,
  "generator": "equal_location_earnings"
},
{
  "name": "Mason",
  "id": "order89",
  "store": "Sprouts Farmers Market",
  "earnings": 20,
  "startingearnings": 20,
  "city": "Oakland",
  "amount": 19,
  "expire": 1,
  "items": {
    "apple": 4,
    "grape": 6,
    "pear": 1,
    "orange": 2,
    "pineapple": 3,
    "kiwi": 3
  },
  "demand": 0,
  "generator": "equal_location_earnings"
},
{
  "name": "Jacob",
  "id": "order90",
  "store": "Sprouts Farmers Market",
  "earnings": 20,
  "startingearnings": 20,
  "city": "Oakland",
  "amount": 14,
  "expire": 1,
  "items": {
    "kiwi": 2,
    "watermelon": 4,
    "pineapple": 3,
    "pear": 2,
    "apple": 2,
    "grape": 1
  },
  "demand": 0,
  "generator": "equal_location_earnings"
},
{
  "name": "Ethan",
  "id": "order91",
  "store": "Sprouts Farmers Market",
  "earnings": 20,
  "startingearnings": 20,
  "city": "Oakland",
  "amount": 3,
  "expire": 1,
  "items": {
    "orange": 1,
    "pineapple": 1,
    "grape": 1
  },
  "demand": 0,
  "generator": "equal_location_earnings"
},
{
  "name": "Liam",
  "id": "order92",
  "store": "Berkeley Bowl",
  "earnings": 17,
  "startingearnings": 17,
  "city": "Berkeley",
  "amount": 14,
  "expire": 1,
  "items": {
    "apple": 2,
    "grape": 4,
    "pineapple": 3,
    "watermelon": 3,
    "orange": 2
  },
  "demand": 0,
  "generator": "pure_randomness"
},
{
  "name": "Sophia",
  "id": "order93",
  "store": "Berkeley Bowl",
  "earnings": 30,
  "startingearnings": 30,
  "city": "Berkeley",
  "amount": 5,
  "expire": 1,
  "items": {
    "apple": 2,
    "watermelon": 2,
    "orange": 1
  },
  "demand": 0,
  "generator": "pure_randomness"
},
{
  "name": "Oliver",
  "id": "order94",
  "store": "Berkeley Bowl",
  "earnings": 21,
  "startingearnings": 21,
  "city": "Berkeley",
  "amount": 7,
  "expire": 1,
  "items": {
    "orange": 1,
    "watermelon": 1,
    "apple": 2,
    "pineapple": 3
  },
  "demand": 0,
  "generator": "pure_randomness"
},
{
  "name": "James",
  "id": "order95",
  "store": "Sprouts Farmers Market",
  "earnings": 2,
  "startingearnings": 2,
  "city": "Oakland",
  "amount": 8,
  "expire": 1,
  "items": {
    "pineapple": 2,
    "grape": 3,
    "kiwi": 2,
    "orange": 1
  },
  "demand": 0,
  "generator": "pure_randomness"
},
{
  "name": "Park",
  "id": "order96",
  "store": "Berkeley Bowl",
  "earnings": 35,
  "startingearnings": 35,
  "city": "Berkeley",
  "amount": 6,
  "expire": 1,
  "items": {
    "watermelon": 2,
    "apple": 3,
    "grape": 1
  },
  "demand": 0,
  "generator": "pure_randomness"
},
{
  "name": "Mia",
  "id": "order97",
  "store": "Safeway",
  "earnings": 20,
  "startingearnings": 20,
  "city": "Piedmont",
  "amount": 2,
  "expire": 1,
  "items": {
    "orange": 1,
    "watermelon": 1
  },
  "demand": 0,
  "generator": "pure_randomness"
},
{
  "name": "Logan",
  "id": "order98",
  "store": "Sprouts Farmers Market",
  "earnings": 36,
  "startingearnings": 36,
  "city": "Oakland",
  "amount": 19,
  "expire": 1,
  "items": {
    "pear": 3,
    "watermelon": 3,
    "orange": 4,
    "kiwi": 2,
    "apple": 3,
    "grape": 1,
    "pineapple": 3
  },
  "demand": 0,
  "generator": "pure_randomness"
},
{
  "name": "Christopher",
  "id": "order99",
  "store": "Berkeley Bowl",
  "earnings": 15,
  "startingearnings": 15,
  "city": "Berkeley",
  "amount": 6,
  "expire": 1,
  "items": {
    "orange": 2,
    "watermelon": 3,
    "apple": 1
  },
  "demand": 0,
  "generator": "pure_randomness"
},
{
  "name": "Jacob",
  "id": "order96",
  "store": "Sprouts Farmers Market",
  "earnings": 20,
  "startingearnings": 20,
  "city": "Oakland",
  "amount": 15,
  "expire": 1,
  "items": {
    "watermelon": 5,
    "apple": 2,
    "grape": 5,
    "orange": 1,
    "pear": 1,
    "pineapple": 1
  },
  "demand": 0,
  "generator": "equal_location_earnings"
},
{
  "name": "Sophia",
  "id": "order97",
  "store": "Sprouts Farmers Market",
  "earnings": 20,
  "startingearnings": 20,
  "city": "Oakland",
  "amount": 4,
  "expire": 1,
  "items": {
    "orange": 1,
    "kiwi": 1,
    "watermelon": 2
  },
  "demand": 0,
  "generator": "equal_location_earnings"
},
{
  "name": "Jacob",
  "id": "order98",
  "store": "Sprouts Farmers Market",
  "earnings": 20,
  "startingearnings": 20,
  "city": "Oakland",
  "amount": 12,
  "expire": 1,
  "items": {
    "pear": 3,
    "orange": 1,
    "kiwi": 3,
    "watermelon": 2,
    "pineapple": 1,
    "grape": 2
  },
  "demand": 0,
  "generator": "equal_location_earnings"
},
{
  "name": "Jacob",
  "id": "order99",
  "store": "Sprouts Farmers Market",
  "earnings": 20,
  "startingearnings": 20,
  "city": "Oakland",
  "amount": 6,
  "expire": 1,
  "items": {
    "kiwi": 2,
    "pineapple": 1,
    "apple": 1,
    "pear": 2
  },
  "demand": 0,
  "generator": "equal_location_earnings"
},
{
  "name": "James",
  "id": "order100",
  "store": "Sprouts Farmers Market",
  "earnings": 20,
  "startingearnings": 20,
  "city": "Oakland",
  "amount": 15,
  "expire": 1,
  "items": {
    "apple": 4,
    "watermelon": 3,
    "grape": 1,
    "kiwi": 3,
    "orange": 3,
    "pineapple": 1
  },
  "demand": 0,
  "generator": "equal_location_earnings"
},
{
  "name": "Park",
  "id": "order101",
  "store": "Sprouts Farmers Market",
  "earnings": 20,
  "startingearnings": 20,
  "city": "Oakland",
  "amount": 18,
  "expire": 1,
  "items": {
    "kiwi": 3,
    "apple": 2,
    "orange": 3,
    "watermelon": 1,
    "grape": 4,
    "pineapple": 2,
    "pear": 3
  },
  "demand": 0,
  "generator": "equal_location_earnings"
},
{
  "name": "Benjamin",
  "id": "order102",
  "store": "Sprouts Farmers Market",
  "earnings": 20,
  "startingearnings": 20,
  "city": "Oakland",
  "amount": 1,
  "expire": 1,
  "items": {
    "orange": 1
  },
  "demand": 0,
  "generator": "equal_location_earnings"
},
{
  "name": "Christopher",
  "id": "order103",
  "store": "Sprouts Farmers Market",
  "earnings": 20,
  "startingearnings": 20,
  "city": "Oakland",
  "amount": 15,
  "expire": 1,
  "items": {
    "watermelon": 5,
    "apple": 4,
    "pear": 2,
    "orange": 2,
    "grape": 1,
    "pineapple": 1
  },
  "demand": 0,
  "generator": "equal_location_earnings"
},
{
  "name": "Park",
  "id": "order104",
  "store": "Sprouts Farmers Market",
  "earnings": 20,
  "startingearnings": 20,
  "city": "Oakland",
  "amount": 8,
  "expire": 1,
  "items": {
    "apple": 6,
    "kiwi": 2
  },
  "demand": 0,
  "generator": "vary_location"
},
{
  "name": "Michael",
  "id": "order105",
  "store": "Target",
  "earnings": 20,
  "startingearnings": 20,
  "city": "Emeryville",
  "amount": 8,
  "expire": 1,
  "items": {
    "banana": 5,
    "pineapple": 3
  },
  "demand": 0,
  "generator": "vary_location"
},
{
  "name": "Ethan",
  "id": "order106",
  "store": "Sprouts Farmers Market",
  "earnings": 20,
  "startingearnings": 20,
  "city": "Oakland",
  "amount": 8,
  "expire": 1,
  "items": {
    "watermelon": 3,
    "pineapple": 5
  },
  "demand": 0,
  "generator": "vary_location"
},
{
  "name": "Jacob",
  "id": "order107",
  "store": "Safeway",
  "earnings": 20,
  "startingearnings": 20,
  "city": "Piedmont",
  "amount": 8,
  "expire": 1,
  "items": {
    "watermelon": 7,
    "apple": 1
  },
  "demand": 0,
  "generator": "vary_location"
},
{
  "name": "Lucas",
  "id": "order108",
  "store": "Sprouts Farmers Market",
  "earnings": 20,
  "startingearnings": 20,
  "city": "Oakland",
  "amount": 5,
  "expire": 1,
  "items": {
    "watermelon": 1,
    "orange": 3,
    "apple": 1
  },
  "demand": 0,
  "generator": "equal_location_earnings"
},
{
  "name": "Olivia",
  "id": "order109",
  "store": "Sprouts Farmers Market",
  "earnings": 20,
  "startingearnings": 20,
  "city": "Oakland",
  "amount": 5,
  "expire": 1,
  "items": {
    "pineapple": 1,
    "pear": 1,
    "kiwi": 1,
    "apple": 1,
    "grape": 1
  },
  "demand": 0,
  "generator": "equal_location_earnings"
},
{
  "name": "Isabella",
  "id": "order110",
  "store": "Sprouts Farmers Market",
  "earnings": 20,
  "startingearnings": 20,
  "city": "Oakland",
  "amount": 13,
  "expire": 1,
  "items": {
    "orange": 3,
    "kiwi": 3,
    "apple": 4,
    "pineapple": 1,
    "watermelon": 1,
    "grape": 1
  },
  "demand": 0,
  "generator": "equal_location_earnings"
},
{
  "name": "Ava",
  "id": "order111",
  "store": "Sprouts Farmers Market",
  "earnings": 20,
  "startingearnings": 20,
  "city": "Oakland",
  "amount": 18,
  "expire": 1,
  "items": {
    "pear": 5,
    "grape": 3,
    "pineapple": 2,
    "kiwi": 3,
    "orange": 2,
    "apple": 2,
    "watermelon": 1
  },
  "demand": 0,
  "generator": "equal_location_earnings"
},
{
  "name": "Oliver",
  "id": "order112",
  "store": "Sprouts Farmers Market",
  "earnings": 30,
  "startingearnings": 30,
  "city": "Oakland",
  "amount": 6,
  "expire": 1,
  "items": {
    "apple": 2,
    "grape": 2,
    "orange": 1,
    "kiwi": 1
  },
  "demand": 0,
  "generator": "pure_randomness"
},
{
  "name": "Olivia",
  "id": "order113",
  "store": "Berkeley Bowl",
  "earnings": 24,
  "startingearnings": 24,
  "city": "Berkeley",
  "amount": 8,
  "expire": 1,
  "items": {
    "pineapple": 1,
    "grape": 2,
    "watermelon": 2,
    "orange": 2,
    "apple": 1
  },
  "demand": 0,
  "generator": "pure_randomness"
},
{
  "name": "Michael",
  "id": "order114",
  "store": "Safeway",
  "earnings": 30,
  "startingearnings": 30,
  "city": "Piedmont",
  "amount": 5,
  "expire": 1,
  "items": {
    "watermelon": 2,
    "orange": 2,
    "apple": 1
  },
  "demand": 0,
  "generator": "pure_randomness"
},
{
  "name": "Ethan",
  "id": "order115",
  "store": "Safeway",
  "earnings": 7,
  "startingearnings": 7,
  "city": "Piedmont",
  "amount": 13,
  "expire": 1,
  "items": {
    "orange": 5,
    "apple": 3,
    "watermelon": 5
  },
  "demand": 0,
  "generator": "pure_randomness"
},
{
  "name": "Joseph",
  "id": "order112",
  "store": "Sprouts Farmers Market",
  "earnings": 20,
  "startingearnings": 20,
  "city": "Oakland",
  "amount": 6,
  "expire": 1,
  "items": {
    "pineapple": 1,
    "pear": 4,
    "orange": 1
  },
  "demand": 0,
  "generator": "equal_everything"
},
{
  "name": "Ethan",
  "id": "order113",
  "store": "Sprouts Farmers Market",
  "earnings": 20,
  "startingearnings": 20,
  "city": "Oakland",
  "amount": 6,
  "expire": 1,
  "items": {
    "kiwi": 3,
    "apple": 1,
    "watermelon": 2
  },
  "demand": 0,
  "generator": "equal_everything"
},
{
  "name": "Charlotte",
  "id": "order114",
  "store": "Sprouts Farmers Market",
  "earnings": 20,
  "startingearnings": 20,
  "city": "Oakland",
  "amount": 6,
  "expire": 1,
  "items": {
    "pear": 4,
    "orange": 1,
    "grape": 1
  },
  "demand": 0,
  "generator": "equal_everything"
},
{
  "name": "Sophia",
  "id": "order115",
  "store": "Sprouts Farmers Market",
  "earnings": 20,
  "startingearnings": 20,
  "city": "Oakland",
  "amount": 6,
  "expire": 1,
  "items": {
    "watermelon": 2,
    "pineapple": 4
  },
  "demand": 0,
  "generator": "equal_everything"
},
{
  "name": "Michael",
  "id": "order116",
  "store": "Sprouts Farmers Market",
  "earnings": 20,
  "startingearnings": 20,
  "city": "Oakland",
  "amount": 12,
  "expire": 1,
  "items": {
    "pineapple": 2,
    "grape": 4,
    "watermelon": 1,
    "apple": 3,
    "kiwi": 2
  },
  "demand": 0,
  "generator": "equal_location_earnings"
},
{
  "name": "Liam",
  "id": "order117",
  "store": "Sprouts Farmers Market",
  "earnings": 20,
  "startingearnings": 20,
  "city": "Oakland",
  "amount": 15,
  "expire": 1,
  "items": {
    "pineapple": 3,
    "orange": 1,
    "watermelon": 4,
    "pear": 5,
    "kiwi": 2
  },
  "demand": 0,
  "generator": "equal_location_earnings"
},
{
  "name": "Ava",
  "id": "order118",
  "store": "Sprouts Farmers Market",
  "earnings": 20,
  "startingearnings": 20,
  "city": "Oakland",
  "amount": 16,
  "expire": 1,
  "items": {
    "apple": 3,
    "pineapple": 2,
    "watermelon": 1,
    "orange": 3,
    "kiwi": 3,
    "grape": 3,
    "pear": 1
  },
  "demand": 0,
  "generator": "equal_location_earnings"
},
{
  "name": "Benjamin",
  "id": "order119",
  "store": "Sprouts Farmers Market",
  "earnings": 20,
  "startingearnings": 20,
  "city": "Oakland",
  "amount": 7,
  "expire": 1,
  "items": {
    "orange": 3,
    "pineapple": 1,
    "grape": 2,
    "kiwi": 1
  },
  "demand": 0,
  "generator": "equal_location_earnings"
},
{
  "name": "Elijah",
  "id": "order120",
  "store": "Berkeley Bowl",
  "earnings": 20,
  "startingearnings": 20,
  "city": "Berkeley",
  "amount": 8,
  "expire": 1,
  "items": {
    "pineapple": 5,
    "watermelon": 3
  },
  "demand": 0,
  "generator": "vary_location"
},
{
  "name": "Ethan",
  "id": "order121",
  "store": "Sprouts Farmers Market",
  "earnings": 20,
  "startingearnings": 20,
  "city": "Oakland",
  "amount": 8,
  "expire": 1,
  "items": {
    "pear": 4,
    "watermelon": 4
  },
  "demand": 0,
  "generator": "vary_location"
},
{
  "name": "Emma",
  "id": "order122",
  "store": "Target",
  "earnings": 20,
  "startingearnings": 20,
  "city": "Emeryville",
  "amount": 8,
  "expire": 1,
  "items": {
    "apple": 4,
    "pineapple": 4
  },
  "demand": 0,
  "generator": "vary_location"
},
{
  "name": "Abigail",
  "id": "order123",
  "store": "Safeway",
  "earnings": 20,
  "startingearnings": 20,
  "city": "Piedmont",
  "amount": 8,
  "expire": 1,
  "items": {
    "apple": 5,
    "watermelon": 3
  },
  "demand": 0,
  "generator": "vary_location"
},
{
  "name": "Olivia",
  "id": "order124",
  "store": "Sprouts Farmers Market",
  "earnings": 20,
  "startingearnings": 20,
  "city": "Oakland",
  "amount": 6,
  "expire": 1,
  "items": {
    "orange": 2,
    "watermelon": 1,
    "pear": 1,
    "apple": 1,
    "grape": 1
  },
  "demand": 0,
  "generator": "equal_location_earnings"
},
{
  "name": "Jacob",
  "id": "order125",
  "store": "Sprouts Farmers Market",
  "earnings": 20,
  "startingearnings": 20,
  "city": "Oakland",
  "amount": 9,
  "expire": 1,
  "items": {
    "pineapple": 1,
    "kiwi": 2,
    "apple": 1,
    "pear": 3,
    "grape": 1,
    "watermelon": 1
  },
  "demand": 0,
  "generator": "equal_location_earnings"
},
{
  "name": "Olivia",
  "id": "order126",
  "store": "Sprouts Farmers Market",
  "earnings": 20,
  "startingearnings": 20,
  "city": "Oakland",
  "amount": 16,
  "expire": 1,
  "items": {
    "apple": 1,
    "kiwi": 5,
    "watermelon": 2,
    "pineapple": 2,
    "pear": 4,
    "orange": 1,
    "grape": 1
  },
  "demand": 0,
  "generator": "equal_location_earnings"
},
{
  "name": "Charlotte",
  "id": "order127",
  "store": "Sprouts Farmers Market",
  "earnings": 20,
  "startingearnings": 20,
  "city": "Oakland",
  "amount": 7,
  "expire": 1,
  "items": {
    "watermelon": 1,
    "pear": 1,
    "apple": 2,
    "grape": 2,
    "kiwi": 1
  },
  "demand": 0,
  "generator": "equal_location_earnings"
},
{
  "name": "Mia",
  "id": "order128",
  "store": "Berkeley Bowl",
  "earnings": 19,
  "startingearnings": 19,
  "city": "Berkeley",
  "amount": 5,
  "expire": 1,
  "items": {
    "apple": 2,
    "orange": 1,
    "watermelon": 1,
    "grape": 1
  },
  "demand": 0,
  "generator": "pure_randomness"
},
{
  "name": "Ethan",
  "id": "order129",
  "store": "Target",
  "earnings": 29,
  "startingearnings": 29,
  "city": "Emeryville",
  "amount": 3,
  "expire": 1,
  "items": {
    "grape": 1,
    "watermelon": 1,
    "pineapple": 1
  },
  "demand": 0,
  "generator": "pure_randomness"
},
{
  "name": "Lucas",
  "id": "order130",
  "store": "Berkeley Bowl",
  "earnings": 20,
  "startingearnings": 20,
  "city": "Berkeley",
  "amount": 2,
  "expire": 1,
  "items": {
    "watermelon": 1,
    "orange": 1
  },
  "demand": 0,
  "generator": "pure_randomness"
},
{
  "name": "Logan",
  "id": "order131",
  "store": "Target",
  "earnings": 2,
  "startingearnings": 2,
  "city": "Emeryville",
  "amount": 5,
  "expire": 1,
  "items": {
    "pineapple": 2,
    "grape": 2,
    "apple": 1
  },
  "demand": 0,
  "generator": "pure_randomness"
},
{
  "name": "David",
  "id": "order128",
  "store": "Safeway",
  "earnings": 36,
  "startingearnings": 36,
  "city": "Piedmont",
  "amount": 4,
  "expire": 1,
  "items": {
    "apple": 2,
    "watermelon": 1,
    "orange": 1
  },
  "demand": 0,
  "generator": "pure_randomness"
},
{
  "name": "Christopher",
  "id": "order129",
  "store": "Berkeley Bowl",
  "earnings": 1,
  "startingearnings": 1,
  "city": "Berkeley",
  "amount": 4,
  "expire": 1,
  "items": {
    "watermelon": 2,
    "apple": 1,
    "grape": 1
  },
  "demand": 0,
  "generator": "pure_randomness"
},
{
  "name": "Mia",
  "id": "order130",
  "store": "Sprouts Farmers Market",
  "earnings": 6,
  "startingearnings": 6,
  "city": "Oakland",
  "amount": 15,
  "expire": 1,
  "items": {
    "orange": 3,
    "pineapple": 1,
    "grape": 6,
    "apple": 2,
    "pear": 3
  },
  "demand": 0,
  "generator": "pure_randomness"
},
{
  "name": "Marcus",
  "id": "order131",
  "store": "Safeway",
  "earnings": 2,
  "startingearnings": 2,
  "city": "Piedmont",
  "amount": 1,
  "expire": 1,
  "items": {
    "orange": 1
  },
  "demand": 0,
  "generator": "pure_randomness"
},
{
  "name": "Daniel",
  "id": "order132",
  "store": "Sprouts Farmers Market",
  "earnings": 20,
  "startingearnings": 20,
  "city": "Oakland",
  "amount": 8,
  "expire": 1,
  "items": {
    "grape": 3,
    "orange": 5
  },
  "demand": 0,
  "generator": "vary_location"
},
{
  "name": "Ava",
  "id": "order133",
  "store": "Berkeley Bowl",
  "earnings": 20,
  "startingearnings": 20,
  "city": "Berkeley",
  "amount": 8,
  "expire": 1,
  "items": {
    "orange": 5,
    "apple": 3
  },
  "demand": 0,
  "generator": "vary_location"
},
{
  "name": "Lucas",
  "id": "order134",
  "store": "Target",
  "earnings": 20,
  "startingearnings": 20,
  "city": "Emeryville",
  "amount": 8,
  "expire": 1,
  "items": {
    "watermelon": 5,
    "grape": 3
  },
  "demand": 0,
  "generator": "vary_location"
},
{
  "name": "Olivia",
  "id": "order135",
  "store": "Berkeley Bowl",
  "earnings": 20,
  "startingearnings": 20,
  "city": "Berkeley",
  "amount": 8,
  "expire": 1,
  "items": {
    "orange": 5,
    "grape": 3
  },
  "demand": 0,
  "generator": "vary_location"
},
{
  "name": "Park",
  "id": "order136",
  "store": "Sprouts Farmers Market",
  "earnings": 20,
  "startingearnings": 20,
  "city": "Oakland",
  "amount": 17,
  "expire": 1,
  "items": {
    "pear": 4,
    "watermelon": 6,
    "kiwi": 3,
    "apple": 1,
    "pineapple": 3
  },
  "demand": 0,
  "generator": "equal_location_earnings"
},
{
  "name": "David",
  "id": "order137",
  "store": "Sprouts Farmers Market",
  "earnings": 20,
  "startingearnings": 20,
  "city": "Oakland",
  "amount": 1,
  "expire": 1,
  "items": {
    "pineapple": 1
  },
  "demand": 0,
  "generator": "equal_location_earnings"
},
{
  "name": "Oliver",
  "id": "order138",
  "store": "Sprouts Farmers Market",
  "earnings": 20,
  "startingearnings": 20,
  "city": "Oakland",
  "amount": 7,
  "expire": 1,
  "items": {
    "kiwi": 2,
    "watermelon": 1,
    "pear": 1,
    "apple": 2,
    "pineapple": 1
  },
  "demand": 0,
  "generator": "equal_location_earnings"
},
{
  "name": "David",
  "id": "order139",
  "store": "Sprouts Farmers Market",
  "earnings": 20,
  "startingearnings": 20,
  "city": "Oakland",
  "amount": 2,
  "expire": 1,
  "items": {
    "kiwi": 1,
    "watermelon": 1
  },
  "demand": 0,
  "generator": "equal_location_earnings"
},
{
  "name": "Elijah",
  "id": "order140",
  "store": "Berkeley Bowl",
  "earnings": 20,
  "startingearnings": 20,
  "city": "Berkeley",
  "amount": 8,
  "expire": 1,
  "items": {
    "orange": 6,
    "watermelon": 2
  },
  "demand": 0,
  "generator": "vary_location"
},
{
  "name": "Mason",
  "id": "order141",
  "store": "Safeway",
  "earnings": 20,
  "startingearnings": 20,
  "city": "Piedmont",
  "amount": 8,
  "expire": 1,
  "items": {
    "apple": 5,
    "watermelon": 3
  },
  "demand": 0,
  "generator": "vary_location"
},
{
  "name": "Ethan",
  "id": "order142",
  "store": "Safeway",
  "earnings": 20,
  "startingearnings": 20,
  "city": "Piedmont",
  "amount": 8,
  "expire": 1,
  "items": {
    "orange": 3,
    "watermelon": 5
  },
  "demand": 0,
  "generator": "vary_location"
},
{
  "name": "Charlotte",
  "id": "order143",
  "store": "Safeway",
  "earnings": 20,
  "startingearnings": 20,
  "city": "Piedmont",
  "amount": 8,
  "expire": 1,
  "items": {
    "watermelon": 4,
    "apple": 4
  },
  "demand": 0,
  "generator": "vary_location"
},
{
  "name": "Evelyn",
  "id": "order144",
  "store": "Target",
  "earnings": 18,
  "startingearnings": 18,
  "city": "Emeryville",
  "amount": 2,
  "expire": 1,
  "items": {
    "pineapple": 1,
    "grape": 1
  },
  "demand": 0,
  "generator": "pure_randomness"
},
{
  "name": "Abigail",
  "id": "order145",
  "store": "Sprouts Farmers Market",
  "earnings": 35,
  "startingearnings": 35,
  "city": "Oakland",
  "amount": 7,
  "expire": 1,
  "items": {
    "pineapple": 1,
    "kiwi": 3,
    "pear": 1,
    "apple": 1,
    "grape": 1
  },
  "demand": 0,
  "generator": "pure_randomness"
},
{
  "name": "Liam",
  "id": "order146",
  "store": "Sprouts Farmers Market",
  "earnings": 38,
  "startingearnings": 38,
  "city": "Oakland",
  "amount": 12,
  "expire": 1,
  "items": {
    "grape": 2,
    "apple": 3,
    "watermelon": 5,
    "pineapple": 2
  },
  "demand": 0,
  "generator": "pure_randomness"
},
{
  "name": "Noah",
  "id": "order147",
  "store": "Sprouts Farmers Market",
  "earnings": 14,
  "startingearnings": 14,
  "city": "Oakland",
  "amount": 4,
  "expire": 1,
  "items": {
    "grape": 1,
    "apple": 1,
    "pear": 2
  },
  "demand": 0,
  "generator": "pure_randomness"
},
{
  "name": "Michael",
  "id": "order144",
  "store": "Sprouts Farmers Market",
  "earnings": 20,
  "startingearnings": 20,
  "city": "Oakland",
  "amount": 15,
  "expire": 1,
  "items": {
    "grape": 3,
    "pear": 3,
    "kiwi": 3,
    "watermelon": 2,
    "apple": 2,
    "pineapple": 2
  },
  "demand": 0,
  "generator": "equal_location_earnings"
},
{
  "name": "Park",
  "id": "order145",
  "store": "Sprouts Farmers Market",
  "earnings": 20,
  "startingearnings": 20,
  "city": "Oakland",
  "amount": 5,
  "expire": 1,
  "items": {
    "kiwi": 1,
    "orange": 2,
    "watermelon": 1,
    "grape": 1
  },
  "demand": 0,
  "generator": "equal_location_earnings"
},
{
  "name": "Marcus",
  "id": "order146",
  "store": "Sprouts Farmers Market",
  "earnings": 20,
  "startingearnings": 20,
  "city": "Oakland",
  "amount": 5,
  "expire": 1,
  "items": {
    "apple": 2,
    "pear": 1,
    "grape": 1,
    "pineapple": 1
  },
  "demand": 0,
  "generator": "equal_location_earnings"
},
{
  "name": "Michael",
  "id": "order147",
  "store": "Sprouts Farmers Market",
  "earnings": 20,
  "startingearnings": 20,
  "city": "Oakland",
  "amount": 7,
  "expire": 1,
  "items": {
    "pineapple": 1,
    "watermelon": 2,
    "apple": 1,
    "pear": 2,
    "grape": 1
  },
  "demand": 0,
  "generator": "equal_location_earnings"
},
{
  "name": "Michael",
  "id": "order148",
  "store": "Sprouts Farmers Market",
  "earnings": 20,
  "startingearnings": 20,
  "city": "Oakland",
  "amount": 19,
  "expire": 1,
  "items": {
    "kiwi": 3,
    "apple": 1,
    "pear": 5,
    "watermelon": 2,
    "grape": 4,
    "orange": 3,
    "pineapple": 1
  },
  "demand": 0,
  "generator": "equal_earnings"
},
{
  "name": "Liam",
  "id": "order149",
  "store": "Safeway",
  "earnings": 20,
  "startingearnings": 20,
  "city": "Piedmont",
  "amount": 8,
  "expire": 1,
  "items": {
    "apple": 2,
    "watermelon": 4,
    "orange": 2
  },
  "demand": 0,
  "generator": "equal_earnings"
},
{
  "name": "Isabella",
  "id": "order150",
  "store": "Target",
  "earnings": 20,
  "startingearnings": 20,
  "city": "Emeryville",
  "amount": 2,
  "expire": 1,
  "items": {
    "pineapple": 1,
    "grape": 1
  },
  "demand": 0,
  "generator": "equal_earnings"
},
{
  "name": "Park",
  "id": "order151",
  "store": "Berkeley Bowl",
  "earnings": 20,
  "startingearnings": 20,
  "city": "Berkeley",
  "amount": 5,
  "expire": 1,
  "items": {
    "apple": 1,
    "orange": 2,
    "watermelon": 1,
    "pineapple": 1
  },
  "demand": 0,
  "generator": "equal_earnings"
},
{
  "name": "Marcus",
  "id": "order152",
  "store": "Berkeley Bowl",
  "earnings": 20,
  "startingearnings": 20,
  "city": "Berkeley",
  "amount": 4,
  "expire": 1,
  "items": {
    "apple": 4
  },
  "demand": 0,
  "generator": "equal_earnings"
},
{
  "name": "Michael",
  "id": "order153",
  "store": "Berkeley Bowl",
  "earnings": 20,
  "startingearnings": 20,
  "city": "Berkeley",
  "amount": 6,
  "expire": 1,
  "items": {
    "orange": 1,
    "watermelon": 1,
    "apple": 2,
    "grape": 2
  },
  "demand": 0,
  "generator": "equal_earnings"
},
{
  "name": "Elijah",
  "id": "order154",
  "store": "Safeway",
  "earnings": 20,
  "startingearnings": 20,
  "city": "Piedmont",
  "amount": 12,
  "expire": 1,
  "items": {
    "watermelon": 4,
    "apple": 7,
    "orange": 1
  },
  "demand": 0,
  "generator": "equal_earnings"
},
{
  "name": "Christopher",
  "id": "order155",
  "store": "Sprouts Farmers Market",
  "earnings": 20,
  "startingearnings": 20,
  "city": "Oakland",
  "amount": 9,
  "expire": 1,
  "items": {
    "grape": 1,
    "kiwi": 2,
    "apple": 1,
    "watermelon": 1,
    "orange": 3,
    "pear": 1
  },
  "demand": 0,
  "generator": "equal_earnings"
},
{
  "name": "Ethan",
  "id": "order156",
  "store": "Sprouts Farmers Market",
  "earnings": 20,
  "startingearnings": 20,
  "city": "Oakland",
  "amount": 4,
  "expire": 1,
  "items": {
    "pear": 1,
    "pineapple": 2,
    "watermelon": 1
  },
  "demand": 0,
  "generator": "equal_location_earnings"
},
{
  "name": "Aiden",
  "id": "order157",
  "store": "Sprouts Farmers Market",
  "earnings": 20,
  "startingearnings": 20,
  "city": "Oakland",
  "amount": 19,
  "expire": 1,
  "items": {
    "watermelon": 1,
    "kiwi": 4,
    "apple": 4,
    "pineapple": 2,
    "grape": 4,
    "pear": 2,
    "orange": 2
  },
  "demand": 0,
  "generator": "equal_location_earnings"
},
{
  "name": "Noah",
  "id": "order158",
  "store": "Sprouts Farmers Market",
  "earnings": 20,
  "startingearnings": 20,
  "city": "Oakland",
  "amount": 10,
  "expire": 1,
  "items": {
    "watermelon": 1,
    "grape": 3,
    "kiwi": 3,
    "orange": 2,
    "pear": 1
  },
  "demand": 0,
  "generator": "equal_location_earnings"
},
{
  "name": "Amelia",
  "id": "order159",
  "store": "Sprouts Farmers Market",
  "earnings": 20,
  "startingearnings": 20,
  "city": "Oakland",
  "amount": 4,
  "expire": 1,
  "items": {
    "watermelon": 1,
    "grape": 2,
    "pear": 1
  },
  "demand": 0,
  "generator": "equal_location_earnings"
},
{
  "name": "Charlotte",
  "id": "order160",
  "store": "Safeway",
  "earnings": 9,
  "startingearnings": 9,
  "city": "Piedmont",
  "amount": 15,
  "expire": 1,
  "items": {
    "watermelon": 7,
    "apple": 6,
    "orange": 2
  },
  "demand": 0,
  "generator": "pure_randomness"
},
{
  "name": "Daniel",
  "id": "order161",
  "store": "Sprouts Farmers Market",
  "earnings": 6,
  "startingearnings": 6,
  "city": "Oakland",
  "amount": 12,
  "expire": 1,
  "items": {
    "pear": 3,
    "watermelon": 1,
    "grape": 3,
    "kiwi": 1,
    "apple": 2,
    "pineapple": 2
  },
  "demand": 0,
  "generator": "pure_randomness"
},
{
  "name": "Liam",
  "id": "order162",
  "store": "Berkeley Bowl",
  "earnings": 23,
  "startingearnings": 23,
  "city": "Berkeley",
  "amount": 8,
  "expire": 1,
  "items": {
    "pineapple": 2,
    "grape": 3,
    "watermelon": 1,
    "orange": 1,
    "apple": 1
  },
  "demand": 0,
  "generator": "pure_randomness"
},
{
  "name": "Isabella",
  "id": "order163",
  "store": "Sprouts Farmers Market",
  "earnings": 23,
  "startingearnings": 23,
  "city": "Oakland",
  "amount": 1,
  "expire": 1,
  "items": {
    "watermelon": 1
  },
  "demand": 0,
  "generator": "pure_randomness"
},
{
  "name": "Michael",
  "id": "order160",
  "store": "Berkeley Bowl",
  "earnings": 20,
  "startingearnings": 20,
  "city": "Berkeley",
  "amount": 8,
  "expire": 1,
  "items": {
    "orange": 2,
    "apple": 6
  },
  "demand": 0,
  "generator": "vary_location"
},
{
  "name": "Alexander",
  "id": "order161",
  "store": "Safeway",
  "earnings": 20,
  "startingearnings": 20,
  "city": "Piedmont",
  "amount": 8,
  "expire": 1,
  "items": {
    "apple": 3,
    "watermelon": 5
  },
  "demand": 0,
  "generator": "vary_location"
},
{
  "name": "Sophia",
  "id": "order162",
  "store": "Target",
  "earnings": 20,
  "startingearnings": 20,
  "city": "Emeryville",
  "amount": 8,
  "expire": 1,
  "items": {
    "pineapple": 4,
    "grape": 4
  },
  "demand": 0,
  "generator": "vary_location"
},
{
  "name": "David",
  "id": "order163",
  "store": "Berkeley Bowl",
  "earnings": 20,
  "startingearnings": 20,
  "city": "Berkeley",
  "amount": 8,
  "expire": 1,
  "items": {
    "apple": 2,
    "pineapple": 6
  },
  "demand": 0,
  "generator": "vary_location"
},
{
  "name": "Michael",
  "id": "order164",
  "store": "Sprouts Farmers Market",
  "earnings": 20,
  "startingearnings": 20,
  "city": "Oakland",
  "amount": 11,
  "expire": 1,
  "items": {
    "pear": 2,
    "pineapple": 3,
    "watermelon": 2,
    "apple": 4
  },
  "demand": 0,
  "generator": "equal_location_earnings"
},
{
  "name": "Oliver",
  "id": "order165",
  "store": "Sprouts Farmers Market",
  "earnings": 20,
  "startingearnings": 20,
  "city": "Oakland",
  "amount": 19,
  "expire": 1,
  "items": {
    "pear": 3,
    "apple": 2,
    "pineapple": 3,
    "grape": 3,
    "watermelon": 3,
    "kiwi": 2,
    "orange": 3
  },
  "demand": 0,
  "generator": "equal_location_earnings"
},
{
  "name": "Daniel",
  "id": "order166",
  "store": "Sprouts Farmers Market",
  "earnings": 20,
  "startingearnings": 20,
  "city": "Oakland",
  "amount": 12,
  "expire": 1,
  "items": {
    "apple": 3,
    "watermelon": 2,
    "pineapple": 2,
    "orange": 1,
    "kiwi": 2,
    "grape": 2
  },
  "demand": 0,
  "generator": "equal_location_earnings"
},
{
  "name": "David",
  "id": "order167",
  "store": "Sprouts Farmers Market",
  "earnings": 20,
  "startingearnings": 20,
  "city": "Oakland",
  "amount": 11,
  "expire": 1,
  "items": {
    "apple": 4,
    "grape": 2,
    "pear": 2,
    "watermelon": 2,
    "kiwi": 1
  },
  "demand": 0,
  "generator": "equal_location_earnings"
},
{
  "name": "Charlotte",
  "id": "order168",
  "store": "Sprouts Farmers Market",
  "earnings": 23,
  "startingearnings": 23,
  "city": "Oakland",
  "amount": 14,
  "expire": 1,
  "items": {
    "pear": 3,
    "grape": 2,
    "apple": 2,
    "orange": 3,
    "pineapple": 2,
    "watermelon": 2
  },
  "demand": 0,
  "generator": "vary_earnings_item_amount"
},
{
  "name": "Olivia",
  "id": "order169",
  "store": "Sprouts Farmers Market",
  "earnings": 8,
  "startingearnings": 8,
  "city": "Oakland",
  "amount": 5,
  "expire": 1,
  "items": {
    "orange": 2,
    "watermelon": 2,
    "pineapple": 1
  },
  "demand": 0,
  "generator": "vary_earnings_item_amount"
},
{
  "name": "Oliver",
  "id": "order170",
  "store": "Sprouts Farmers Market",
  "earnings": 9,
  "startingearnings": 9,
  "city": "Oakland",
  "amount": 11,
  "expire": 1,
  "items": {
    "pear": 2,
    "pineapple": 2,
    "orange": 2,
    "grape": 1,
    "apple": 3,
    "kiwi": 1
  },
  "demand": 0,
  "generator": "vary_earnings_item_amount"
},
{
  "name": "Isabella",
  "id": "order171",
  "store": "Sprouts Farmers Market",
  "earnings": 16,
  "startingearnings": 16,
  "city": "Oakland",
  "amount": 13,
  "expire": 1,
  "items": {
    "watermelon": 5,
    "apple": 1,
    "pineapple": 2,
    "kiwi": 2,
    "grape": 1,
    "pear": 2
  },
  "demand": 0,
  "generator": "vary_earnings_item_amount"
},
{
  "name": "Joseph",
  "id": "order172",
  "store": "Target",
  "earnings": 20,
  "startingearnings": 20,
  "city": "Emeryville",
  "amount": 8,
  "expire": 1,
  "items": {
    "pineapple": 5,
    "banana": 3
  },
  "demand": 0,
  "generator": "vary_location"
},
{
  "name": "Amelia",
  "id": "order173",
  "store": "Target",
  "earnings": 20,
  "startingearnings": 20,
  "city": "Emeryville",
  "amount": 8,
  "expire": 1,
  "items": {
    "pineapple": 7,
    "grape": 1
  },
  "demand": 0,
  "generator": "vary_location"
},
{
  "name": "Ethan",
  "id": "order174",
  "store": "Target",
  "earnings": 20,
  "startingearnings": 20,
  "city": "Emeryville",
  "amount": 8,
  "expire": 1,
  "items": {
    "apple": 6,
    "grape": 2
  },
  "demand": 0,
  "generator": "vary_location"
},
{
  "name": "Ethan",
  "id": "order175",
  "store": "Sprouts Farmers Market",
  "earnings": 20,
  "startingearnings": 20,
  "city": "Oakland",
  "amount": 8,
  "expire": 1,
  "items": {
    "watermelon": 5,
    "kiwi": 3
  },
  "demand": 0,
  "generator": "vary_location"
},
{
  "name": "Alexander",
  "id": "order176",
  "store": "Target",
  "earnings": 34,
  "startingearnings": 34,
  "city": "Emeryville",
  "amount": 14,
  "expire": 1,
  "items": {
    "grape": 3,
    "banana": 2,
    "pineapple": 2,
    "watermelon": 4,
    "apple": 3
  },
  "demand": 0,
  "generator": "pure_randomness"
},
{
  "name": "Benjamin",
  "id": "order177",
  "store": "Sprouts Farmers Market",
  "earnings": 3,
  "startingearnings": 3,
  "city": "Oakland",
  "amount": 14,
  "expire": 1,
  "items": {
    "orange": 3,
    "pineapple": 3,
    "apple": 2,
    "kiwi": 3,
    "pear": 2,
    "watermelon": 1
  },
  "demand": 0,
  "generator": "pure_randomness"
},
{
  "name": "Mia",
  "id": "order178",
  "store": "Sprouts Farmers Market",
  "earnings": 21,
  "startingearnings": 21,
  "city": "Oakland",
  "amount": 9,
  "expire": 1,
  "items": {
    "orange": 3,
    "pineapple": 3,
    "apple": 1,
    "pear": 1,
    "grape": 1
  },
  "demand": 0,
  "generator": "pure_randomness"
},
{
  "name": "Joseph",
  "id": "order179",
  "store": "Berkeley Bowl",
  "earnings": 8,
  "startingearnings": 8,
  "city": "Berkeley",
  "amount": 1,
  "expire": 1,
  "items": {
    "apple": 1
  },
  "demand": 0,
  "generator": "pure_randomness"
},
{
  "name": "Elijah",
  "id": "order176",
  "store": "Sprouts Farmers Market",
  "earnings": 20,
  "startingearnings": 20,
  "city": "Oakland",
  "amount": 6,
  "expire": 1,
  "items": {
    "kiwi": 4,
    "pineapple": 1,
    "grape": 1
  },
  "demand": 0,
  "generator": "equal_everything"
},
{
  "name": "Liam",
  "id": "order177",
  "store": "Sprouts Farmers Market",
  "earnings": 20,
  "startingearnings": 20,
  "city": "Oakland",
  "amount": 6,
  "expire": 1,
  "items": {
    "orange": 3,
    "grape": 3
  },
  "demand": 0,
  "generator": "equal_everything"
},
{
  "name": "Alexander",
  "id": "order178",
  "store": "Sprouts Farmers Market",
  "earnings": 20,
  "startingearnings": 20,
  "city": "Oakland",
  "amount": 6,
  "expire": 1,
  "items": {
    "orange": 2,
    "apple": 2,
    "pear": 2
  },
  "demand": 0,
  "generator": "equal_everything"
},
{
  "name": "Christopher",
  "id": "order179",
  "store": "Sprouts Farmers Market",
  "earnings": 20,
  "startingearnings": 20,
  "city": "Oakland",
  "amount": 6,
  "expire": 1,
  "items": {
    "pineapple": 2,
    "pear": 3,
    "kiwi": 1
  },
  "demand": 0,
  "generator": "equal_everything"
},
{
  "name": "Daniel",
  "id": "order180",
  "store": "Sprouts Farmers Market",
  "earnings": 10,
  "startingearnings": 10,
  "city": "Oakland",
  "amount": 19,
  "expire": 1,
  "items": {
    "pear": 4,
    "pineapple": 5,
    "kiwi": 7,
    "grape": 2,
    "watermelon": 1
  },
  "demand": 0,
  "generator": "vary_earnings_item_amount"
},
{
  "name": "Liam",
  "id": "order181",
  "store": "Sprouts Farmers Market",
  "earnings": 14,
  "startingearnings": 14,
  "city": "Oakland",
  "amount": 2,
  "expire": 1,
  "items": {
    "orange": 1,
    "watermelon": 1
  },
  "demand": 0,
  "generator": "vary_earnings_item_amount"
},
{
  "name": "Liam",
  "id": "order182",
  "store": "Sprouts Farmers Market",
  "earnings": 13,
  "startingearnings": 13,
  "city": "Oakland",
  "amount": 11,
  "expire": 1,
  "items": {
    "orange": 1,
    "apple": 4,
    "watermelon": 3,
    "grape": 1,
    "pineapple": 2
  },
  "demand": 0,
  "generator": "vary_earnings_item_amount"
},
{
  "name": "Emma",
  "id": "order183",
  "store": "Sprouts Farmers Market",
  "earnings": 29,
  "startingearnings": 29,
  "city": "Oakland",
  "amount": 19,
  "expire": 1,
  "items": {
    "pear": 5,
    "kiwi": 5,
    "pineapple": 5,
    "watermelon": 2,
    "apple": 2
  },
  "demand": 0,
  "generator": "vary_earnings_item_amount"
},
{
  "name": "Ethan",
  "id": "order184",
  "store": "Sprouts Farmers Market",
  "earnings": 20,
  "startingearnings": 20,
  "city": "Oakland",
  "amount": 1,
  "expire": 1,
  "items": {
    "apple": 1
  },
  "demand": 0,
  "generator": "equal_location_earnings"
},
{
  "name": "Logan",
  "id": "order185",
  "store": "Sprouts Farmers Market",
  "earnings": 20,
  "startingearnings": 20,
  "city": "Oakland",
  "amount": 13,
  "expire": 1,
  "items": {
    "grape": 2,
    "pineapple": 3,
    "orange": 2,
    "apple": 2,
    "kiwi": 1,
    "pear": 3
  },
  "demand": 0,
  "generator": "equal_location_earnings"
},
{
  "name": "Lucas",
  "id": "order186",
  "store": "Sprouts Farmers Market",
  "earnings": 20,
  "startingearnings": 20,
  "city": "Oakland",
  "amount": 3,
  "expire": 1,
  "items": {
    "watermelon": 2,
    "grape": 1
  },
  "demand": 0,
  "generator": "equal_location_earnings"
},
{
  "name": "Ava",
  "id": "order187",
  "store": "Sprouts Farmers Market",
  "earnings": 20,
  "startingearnings": 20,
  "city": "Oakland",
  "amount": 3,
  "expire": 1,
  "items": {
    "watermelon": 1,
    "apple": 1,
    "kiwi": 1
  },
  "demand": 0,
  "generator": "equal_location_earnings"
},
{
  "name": "Alexander",
  "id": "order188",
  "store": "Safeway",
  "earnings": 34,
  "startingearnings": 34,
  "city": "Piedmont",
  "amount": 8,
  "expire": 1,
  "items": {
    "watermelon": 4,
    "apple": 3,
    "orange": 1
  },
  "demand": 0,
  "generator": "pure_randomness"
},
{
  "name": "Marcus",
  "id": "order189",
  "store": "Sprouts Farmers Market",
  "earnings": 35,
  "startingearnings": 35,
  "city": "Oakland",
  "amount": 15,
  "expire": 1,
  "items": {
    "apple": 1,
    "pear": 4,
    "watermelon": 3,
    "orange": 2,
    "kiwi": 2,
    "grape": 2,
    "pineapple": 1
  },
  "demand": 0,
  "generator": "pure_randomness"
},
{
  "name": "Ethan",
  "id": "order190",
  "store": "Berkeley Bowl",
  "earnings": 11,
  "startingearnings": 11,
  "city": "Berkeley",
  "amount": 14,
  "expire": 1,
  "items": {
    "orange": 4,
    "grape": 4,
    "watermelon": 4,
    "pineapple": 2
  },
  "demand": 0,
  "generator": "pure_randomness"
},
{
  "name": "Joseph",
  "id": "order191",
  "store": "Safeway",
  "earnings": 4,
  "startingearnings": 4,
  "city": "Piedmont",
  "amount": 13,
  "expire": 1,
  "items": {
    "orange": 8,
    "watermelon": 1,
    "apple": 4
  },
  "demand": 0,
  "generator": "pure_randomness"
},
{
  "name": "Oliver",
  "id": "order192",
  "store": "Sprouts Farmers Market",
  "earnings": 20,
  "startingearnings": 20,
  "city": "Oakland",
  "amount": 2,
  "expire": 1,
  "items": {
    "apple": 1,
    "grape": 1
  },
  "demand": 0,
  "generator": "pure_randomness"
},
{
  "name": "Michael",
  "id": "order193",
  "store": "Target",
  "earnings": 7,
  "startingearnings": 7,
  "city": "Emeryville",
  "amount": 6,
  "expire": 1,
  "items": {
    "banana": 2,
    "watermelon": 1,
    "apple": 1,
    "pineapple": 1,
    "grape": 1
  },
  "demand": 0,
  "generator": "pure_randomness"
},
{
  "name": "Charlotte",
  "id": "order194",
  "store": "Target",
  "earnings": 12,
  "startingearnings": 12,
  "city": "Emeryville",
  "amount": 18,
  "expire": 1,
  "items": {
    "grape": 4,
    "pineapple": 6,
    "watermelon": 2,
    "banana": 3,
    "apple": 3
  },
  "demand": 0,
  "generator": "pure_randomness"
},
{
  "name": "Marcus",
  "id": "order195",
  "store": "Sprouts Farmers Market",
  "earnings": 29,
  "startingearnings": 29,
  "city": "Oakland",
  "amount": 2,
  "expire": 1,
  "items": {
    "watermelon": 1,
    "grape": 1
  },
  "demand": 0,
  "generator": "pure_randomness"
},
{
  "name": "William",
  "id": "order192",
  "store": "Sprouts Farmers Market",
  "earnings": 20,
  "startingearnings": 20,
  "city": "Oakland",
  "amount": 6,
  "expire": 1,
  "items": {
    "kiwi": 1,
    "grape": 1,
    "pear": 1,
    "pineapple": 2,
    "watermelon": 1
  },
  "demand": 0,
  "generator": "equal_location_earnings"
},
{
  "name": "Olivia",
  "id": "order193",
  "store": "Sprouts Farmers Market",
  "earnings": 20,
  "startingearnings": 20,
  "city": "Oakland",
  "amount": 5,
  "expire": 1,
  "items": {
    "kiwi": 1,
    "pineapple": 1,
    "grape": 1,
    "orange": 2
  },
  "demand": 0,
  "generator": "equal_location_earnings"
},
{
  "name": "Jacob",
  "id": "order194",
  "store": "Sprouts Farmers Market",
  "earnings": 20,
  "startingearnings": 20,
  "city": "Oakland",
  "amount": 14,
  "expire": 1,
  "items": {
    "pear": 2,
    "watermelon": 2,
    "orange": 4,
    "kiwi": 3,
    "apple": 2,
    "grape": 1
  },
  "demand": 0,
  "generator": "equal_location_earnings"
},
{
  "name": "Amelia",
  "id": "order195",
  "store": "Sprouts Farmers Market",
  "earnings": 20,
  "startingearnings": 20,
  "city": "Oakland",
  "amount": 18,
  "expire": 1,
  "items": {
    "grape": 1,
    "pineapple": 2,
    "pear": 2,
    "apple": 2,
    "kiwi": 3,
    "watermelon": 5,
    "orange": 3
  },
  "demand": 0,
  "generator": "equal_location_earnings"
},
{
  "name": "Abigail",
  "id": "order196",
  "store": "Berkeley Bowl",
  "earnings": 20,
  "startingearnings": 20,
  "city": "Berkeley",
  "amount": 15,
  "expire": 1,
  "items": {
    "watermelon": 4,
    "grape": 5,
    "apple": 5,
    "pineapple": 1
  },
  "demand": 0,
  "generator": "equal_earnings"
},
{
  "name": "Lucas",
  "id": "order197",
  "store": "Sprouts Farmers Market",
  "earnings": 20,
  "startingearnings": 20,
  "city": "Oakland",
  "amount": 5,
  "expire": 1,
  "items": {
    "grape": 3,
    "watermelon": 1,
    "apple": 1
  },
  "demand": 0,
  "generator": "equal_earnings"
},
{
  "name": "Mason",
  "id": "order198",
  "store": "Safeway",
  "earnings": 20,
  "startingearnings": 20,
  "city": "Piedmont",
  "amount": 2,
  "expire": 1,
  "items": {
    "watermelon": 1,
    "orange": 1
  },
  "demand": 0,
  "generator": "equal_earnings"
},
{
  "name": "Park",
  "id": "order199",
  "store": "Target",
  "earnings": 20,
  "startingearnings": 20,
  "city": "Emeryville",
  "amount": 16,
  "expire": 1,
  "items": {
    "pineapple": 4,
    "apple": 2,
    "banana": 6,
    "watermelon": 2,
    "grape": 2
  },
  "demand": 0,
  "generator": "equal_earnings"
},
{
  "name": "Charlotte",
  "id": "order200",
  "store": "Sprouts Farmers Market",
  "earnings": 20,
  "startingearnings": 20,
  "city": "Oakland",
  "amount": 13,
  "expire": 1,
  "items": {
    "kiwi": 2,
    "apple": 3,
    "orange": 2,
    "pear": 2,
    "pineapple": 3,
    "grape": 1
  },
  "demand": 0,
  "generator": "equal_location_earnings"
},
{
  "name": "James",
  "id": "order201",
  "store": "Sprouts Farmers Market",
  "earnings": 20,
  "startingearnings": 20,
  "city": "Oakland",
  "amount": 1,
  "expire": 1,
  "items": {
    "pear": 1
  },
  "demand": 0,
  "generator": "equal_location_earnings"
},
{
  "name": "Lucas",
  "id": "order202",
  "store": "Sprouts Farmers Market",
  "earnings": 20,
  "startingearnings": 20,
  "city": "Oakland",
  "amount": 14,
  "expire": 1,
  "items": {
    "grape": 2,
    "pear": 3,
    "pineapple": 2,
    "watermelon": 3,
    "kiwi": 1,
    "apple": 2,
    "orange": 1
  },
  "demand": 0,
  "generator": "equal_location_earnings"
},
{
  "name": "Emma",
  "id": "order203",
  "store": "Sprouts Farmers Market",
  "earnings": 20,
  "startingearnings": 20,
  "city": "Oakland",
  "amount": 14,
  "expire": 1,
  "items": {
    "orange": 3,
    "grape": 2,
    "watermelon": 2,
    "pineapple": 3,
    "pear": 3,
    "kiwi": 1
  },
  "demand": 0,
  "generator": "equal_location_earnings"
},
{
  "name": "Mason",
  "id": "order204",
  "store": "Sprouts Farmers Market",
  "earnings": 20,
  "startingearnings": 20,
  "city": "Oakland",
  "amount": 17,
  "expire": 1,
  "items": {
    "pineapple": 4,
    "orange": 3,
    "apple": 2,
    "watermelon": 2,
    "grape": 4,
    "pear": 2
  },
  "demand": 0,
  "generator": "equal_location_earnings"
},
{
  "name": "Emma",
  "id": "order205",
  "store": "Sprouts Farmers Market",
  "earnings": 20,
  "startingearnings": 20,
  "city": "Oakland",
  "amount": 11,
  "expire": 1,
  "items": {
    "pear": 2,
    "watermelon": 1,
    "kiwi": 4,
    "pineapple": 2,
    "orange": 1,
    "apple": 1
  },
  "demand": 0,
  "generator": "equal_location_earnings"
},
{
  "name": "Ava",
  "id": "order206",
  "store": "Sprouts Farmers Market",
  "earnings": 20,
  "startingearnings": 20,
  "city": "Oakland",
  "amount": 12,
  "expire": 1,
  "items": {
    "grape": 3,
    "orange": 3,
    "pear": 1,
    "apple": 4,
    "watermelon": 1
  },
  "demand": 0,
  "generator": "equal_location_earnings"
},
{
  "name": "Olivia",
  "id": "order207",
  "store": "Sprouts Farmers Market",
  "earnings": 20,
  "startingearnings": 20,
  "city": "Oakland",
  "amount": 9,
  "expire": 1,
  "items": {
    "watermelon": 1,
    "kiwi": 2,
    "pear": 3,
    "grape": 1,
    "pineapple": 1,
    "apple": 1
  },
  "demand": 0,
  "generator": "equal_location_earnings"
},
{
  "name": "Elijah",
  "id": "order208",
  "store": "Target",
  "earnings": 22,
  "startingearnings": 22,
  "city": "Emeryville",
  "amount": 19,
  "expire": 1,
  "items": {
    "pineapple": 5,
    "watermelon": 7,
    "apple": 2,
    "grape": 4,
    "banana": 1
  },
  "demand": 0,
  "generator": "pure_randomness"
},
{
  "name": "Joseph",
  "id": "order209",
  "store": "Sprouts Farmers Market",
  "earnings": 31,
  "startingearnings": 31,
  "city": "Oakland",
  "amount": 17,
  "expire": 1,
  "items": {
    "grape": 3,
    "watermelon": 3,
    "apple": 2,
    "pineapple": 4,
    "kiwi": 2,
    "orange": 2,
    "pear": 1
  },
  "demand": 0,
  "generator": "pure_randomness"
},
{
  "name": "Ava",
  "id": "order210",
  "store": "Target",
  "earnings": 18,
  "startingearnings": 18,
  "city": "Emeryville",
  "amount": 13,
  "expire": 1,
  "items": {
    "pineapple": 4,
    "watermelon": 3,
    "grape": 3,
    "apple": 3
  },
  "demand": 0,
  "generator": "pure_randomness"
},
{
  "name": "Christopher",
  "id": "order211",
  "store": "Target",
  "earnings": 35,
  "startingearnings": 35,
  "city": "Emeryville",
  "amount": 9,
  "expire": 1,
  "items": {
    "pineapple": 2,
    "apple": 3,
    "banana": 2,
    "grape": 2
  },
  "demand": 0,
  "generator": "pure_randomness"
},
{
  "name": "Michael",
  "id": "order208",
  "store": "Sprouts Farmers Market",
  "earnings": 30,
  "startingearnings": 30,
  "city": "Oakland",
  "amount": 3,
  "expire": 1,
  "items": {
    "pineapple": 2,
    "apple": 1
  },
  "demand": 0,
  "generator": "vary_earnings_item_amount"
},
{
  "name": "Oliver",
  "id": "order209",
  "store": "Sprouts Farmers Market",
  "earnings": 25,
  "startingearnings": 25,
  "city": "Oakland",
  "amount": 4,
  "expire": 1,
  "items": {
    "watermelon": 3,
    "orange": 1
  },
  "demand": 0,
  "generator": "vary_earnings_item_amount"
},
{
  "name": "Ethan",
  "id": "order210",
  "store": "Sprouts Farmers Market",
  "earnings": 4,
  "startingearnings": 4,
  "city": "Oakland",
  "amount": 7,
  "expire": 1,
  "items": {
    "grape": 1,
    "watermelon": 2,
    "pear": 2,
    "orange": 2
  },
  "demand": 0,
  "generator": "vary_earnings_item_amount"
},
{
  "name": "Charlotte",
  "id": "order211",
  "store": "Sprouts Farmers Market",
  "earnings": 18,
  "startingearnings": 18,
  "city": "Oakland",
  "amount": 6,
  "expire": 1,
  "items": {
    "apple": 1,
    "orange": 1,
    "pineapple": 1,
    "grape": 1,
    "watermelon": 1,
    "pear": 1
  },
  "demand": 0,
  "generator": "vary_earnings_item_amount"
},
{
  "name": "Christopher",
  "id": "order212",
  "store": "Sprouts Farmers Market",
  "earnings": 20,
  "startingearnings": 20,
  "city": "Oakland",
  "amount": 10,
  "expire": 1,
  "items": {
    "orange": 1,
    "grape": 3,
    "kiwi": 3,
    "pear": 1,
    "apple": 2
  },
  "demand": 0,
  "generator": "equal_location_earnings"
},
{
  "name": "Jacob",
  "id": "order213",
  "store": "Sprouts Farmers Market",
  "earnings": 20,
  "startingearnings": 20,
  "city": "Oakland",
  "amount": 17,
  "expire": 1,
  "items": {
    "pear": 4,
    "kiwi": 3,
    "apple": 3,
    "watermelon": 1,
    "grape": 3,
    "pineapple": 2,
    "orange": 1
  },
  "demand": 0,
  "generator": "equal_location_earnings"
},
{
  "name": "William",
  "id": "order214",
  "store": "Sprouts Farmers Market",
  "earnings": 20,
  "startingearnings": 20,
  "city": "Oakland",
  "amount": 1,
  "expire": 1,
  "items": {
    "grape": 1
  },
  "demand": 0,
  "generator": "equal_location_earnings"
},
{
  "name": "Logan",
  "id": "order215",
  "store": "Sprouts Farmers Market",
  "earnings": 20,
  "startingearnings": 20,
  "city": "Oakland",
  "amount": 1,
  "expire": 1,
  "items": {
    "apple": 1
  },
  "demand": 0,
  "generator": "equal_location_earnings"
},
{
  "name": "Lucas",
  "id": "order216",
  "store": "Berkeley Bowl",
  "earnings": 20,
  "startingearnings": 20,
  "city": "Berkeley",
  "amount": 8,
  "expire": 1,
  "items": {
    "orange": 5,
    "grape": 3
  },
  "demand": 0,
  "generator": "vary_location"
},
{
  "name": "Noah",
  "id": "order217",
  "store": "Target",
  "earnings": 20,
  "startingearnings": 20,
  "city": "Emeryville",
  "amount": 8,
  "expire": 1,
  "items": {
    "apple": 5,
    "grape": 3
  },
  "demand": 0,
  "generator": "vary_location"
},
{
  "name": "Aiden",
  "id": "order218",
  "store": "Sprouts Farmers Market",
  "earnings": 20,
  "startingearnings": 20,
  "city": "Oakland",
  "amount": 8,
  "expire": 1,
  "items": {
    "pineapple": 4,
    "grape": 4
  },
  "demand": 0,
  "generator": "vary_location"
},
{
  "name": "Aiden",
  "id": "order219",
  "store": "Berkeley Bowl",
  "earnings": 20,
  "startingearnings": 20,
  "city": "Berkeley",
  "amount": 8,
  "expire": 1,
  "items": {
    "apple": 5,
    "orange": 3
  },
  "demand": 0,
  "generator": "vary_location"
},
{
  "name": "Ethan",
  "id": "order220",
  "store": "Target",
  "earnings": 20,
  "startingearnings": 20,
  "city": "Emeryville",
  "amount": 8,
  "expire": 1,
  "items": {
    "apple": 5,
    "watermelon": 3
  },
  "demand": 0,
  "generator": "vary_location"
},
{
  "name": "Park",
  "id": "order221",
  "store": "Target",
  "earnings": 20,
  "startingearnings": 20,
  "city": "Emeryville",
  "amount": 8,
  "expire": 1,
  "items": {
    "watermelon": 4,
    "grape": 4
  },
  "demand": 0,
  "generator": "vary_location"
},
{
  "name": "Liam",
  "id": "order222",
  "store": "Berkeley Bowl",
  "earnings": 20,
  "startingearnings": 20,
  "city": "Berkeley",
  "amount": 8,
  "expire": 1,
  "items": {
    "pineapple": 4,
    "orange": 4
  },
  "demand": 0,
  "generator": "vary_location"
},
{
  "name": "Ethan",
  "id": "order223",
  "store": "Target",
  "earnings": 20,
  "startingearnings": 20,
  "city": "Emeryville",
  "amount": 8,
  "expire": 1,
  "items": {
    "apple": 3,
    "banana": 5
  },
  "demand": 0,
  "generator": "vary_location"
},
{
  "name": "Mason",
  "id": "order224",
  "store": "Berkeley Bowl",
  "earnings": 37,
  "startingearnings": 37,
  "city": "Berkeley",
  "amount": 16,
  "expire": 1,
  "items": {
    "grape": 4,
    "orange": 5,
    "watermelon": 4,
    "pineapple": 1,
    "apple": 2
  },
  "demand": 0,
  "generator": "pure_randomness"
},
{
  "name": "Benjamin",
  "id": "order225",
  "store": "Target",
  "earnings": 6,
  "startingearnings": 6,
  "city": "Emeryville",
  "amount": 14,
  "expire": 1,
  "items": {
    "watermelon": 4,
    "grape": 4,
    "pineapple": 4,
    "apple": 2
  },
  "demand": 0,
  "generator": "pure_randomness"
},
{
  "name": "Joseph",
  "id": "order226",
  "store": "Berkeley Bowl",
  "earnings": 19,
  "startingearnings": 19,
  "city": "Berkeley",
  "amount": 14,
  "expire": 1,
  "items": {
    "apple": 6,
    "pineapple": 4,
    "watermelon": 3,
    "grape": 1
  },
  "demand": 0,
  "generator": "pure_randomness"
},
{
  "name": "Elijah",
  "id": "order227",
  "store": "Berkeley Bowl",
  "earnings": 10,
  "startingearnings": 10,
  "city": "Berkeley",
  "amount": 14,
  "expire": 1,
  "items": {
    "orange": 4,
    "apple": 3,
    "watermelon": 4,
    "grape": 3
  },
  "demand": 0,
  "generator": "pure_randomness"
},
{
  "name": "Isabella",
  "id": "order224",
  "store": "Sprouts Farmers Market",
  "earnings": 33,
  "startingearnings": 33,
  "city": "Oakland",
  "amount": 10,
  "expire": 1,
  "items": {
    "grape": 1,
    "pear": 3,
    "apple": 2,
    "pineapple": 1,
    "watermelon": 2,
    "orange": 1
  },
  "demand": 0,
  "generator": "vary_earnings_item_amount"
},
{
  "name": "Charlotte",
  "id": "order225",
  "store": "Sprouts Farmers Market",
  "earnings": 28,
  "startingearnings": 28,
  "city": "Oakland",
  "amount": 15,
  "expire": 1,
  "items": {
    "grape": 5,
    "orange": 2,
    "apple": 2,
    "watermelon": 1,
    "pear": 2,
    "pineapple": 3
  },
  "demand": 0,
  "generator": "vary_earnings_item_amount"
},
{
  "name": "Evelyn",
  "id": "order226",
  "store": "Sprouts Farmers Market",
  "earnings": 26,
  "startingearnings": 26,
  "city": "Oakland",
  "amount": 16,
  "expire": 1,
  "items": {
    "orange": 3,
    "kiwi": 3,
    "pineapple": 4,
    "pear": 2,
    "grape": 1,
    "watermelon": 3
  },
  "demand": 0,
  "generator": "vary_earnings_item_amount"
},
{
  "name": "William",
  "id": "order227",
  "store": "Sprouts Farmers Market",
  "earnings": 30,
  "startingearnings": 30,
  "city": "Oakland",
  "amount": 8,
  "expire": 1,
  "items": {
    "orange": 3,
    "kiwi": 3,
    "pear": 1,
    "watermelon": 1
  },
  "demand": 0,
  "generator": "vary_earnings_item_amount"
},
{
  "name": "Ava",
  "id": "order228",
  "store": "Sprouts Farmers Market",
  "earnings": 20,
  "startingearnings": 20,
  "city": "Oakland",
  "amount": 15,
  "expire": 1,
  "items": {
    "apple": 4,
    "kiwi": 3,
    "watermelon": 3,
    "grape": 4,
    "pear": 1
  },
  "demand": 0,
  "generator": "commonsense_item_amount"
},
{
  "name": "Mason",
  "id": "order229",
  "store": "Sprouts Farmers Market",
  "earnings": 20,
  "startingearnings": 20,
  "city": "Oakland",
  "amount": 15,
  "expire": 1,
  "items": {
    "pineapple": 6,
    "pear": 3,
    "watermelon": 2,
    "apple": 3,
    "kiwi": 1
  },
  "demand": 0,
  "generator": "commonsense_item_amount"
},
{
  "name": "Matthew",
  "id": "order230",
  "store": "Sprouts Farmers Market",
  "earnings": 20,
  "startingearnings": 20,
  "city": "Oakland",
  "amount": 5,
  "expire": 1,
  "items": {
    "grape": 3,
    "apple": 2
  },
  "demand": 0,
  "generator": "commonsense_item_amount"
},
{
  "name": "David",
  "id": "order231",
  "store": "Sprouts Farmers Market",
  "earnings": 20,
  "startingearnings": 20,
  "city": "Oakland",
  "amount": 15,
  "expire": 1,
  "items": {
    "pineapple": 5,
    "pear": 4,
    "kiwi": 4,
    "watermelon": 2
  },
  "demand": 0,
  "generator": "commonsense_item_amount"
},
{
  "name": "Liam",
  "id": "order232",
  "store": "Sprouts Farmers Market",
  "earnings": 20,
  "startingearnings": 20,
  "city": "Oakland",
  "amount": 16,
  "expire": 1,
  "items": {
    "pineapple": 3,
    "pear": 3,
    "grape": 3,
    "orange": 2,
    "apple": 2,
    "kiwi": 3
  },
  "demand": 0,
  "generator": "equal_location_earnings"
},
{
  "name": "Sophia",
  "id": "order233",
  "store": "Sprouts Farmers Market",
  "earnings": 20,
  "startingearnings": 20,
  "city": "Oakland",
  "amount": 6,
  "expire": 1,
  "items": {
    "apple": 1,
    "kiwi": 4,
    "pear": 1
  },
  "demand": 0,
  "generator": "equal_location_earnings"
},
{
  "name": "Emma",
  "id": "order234",
  "store": "Sprouts Farmers Market",
  "earnings": 20,
  "startingearnings": 20,
  "city": "Oakland",
  "amount": 17,
  "expire": 1,
  "items": {
    "grape": 3,
    "kiwi": 3,
    "orange": 5,
    "watermelon": 3,
    "pear": 2,
    "apple": 1
  },
  "demand": 0,
  "generator": "equal_location_earnings"
},
{
  "name": "Aiden",
  "id": "order235",
  "store": "Sprouts Farmers Market",
  "earnings": 20,
  "startingearnings": 20,
  "city": "Oakland",
  "amount": 1,
  "expire": 1,
  "items": {
    "kiwi": 1
  },
  "demand": 0,
  "generator": "equal_location_earnings"
},
{
  "name": "Charlotte",
  "id": "order236",
  "store": "Sprouts Farmers Market",
  "earnings": 20,
  "startingearnings": 20,
  "city": "Oakland",
  "amount": 6,
  "expire": 1,
  "items": {
    "pear": 2,
    "orange": 3,
    "pineapple": 1
  },
  "demand": 0,
  "generator": "equal_everything"
},
{
  "name": "David",
  "id": "order237",
  "store": "Sprouts Farmers Market",
  "earnings": 20,
  "startingearnings": 20,
  "city": "Oakland",
  "amount": 6,
  "expire": 1,
  "items": {
    "kiwi": 4,
    "grape": 1,
    "orange": 1
  },
  "demand": 0,
  "generator": "equal_everything"
},
{
  "name": "Logan",
  "id": "order238",
  "store": "Sprouts Farmers Market",
  "earnings": 20,
  "startingearnings": 20,
  "city": "Oakland",
  "amount": 6,
  "expire": 1,
  "items": {
    "grape": 1,
    "pear": 4,
    "orange": 1
  },
  "demand": 0,
  "generator": "equal_everything"
},
{
  "name": "Amelia",
  "id": "order239",
  "store": "Sprouts Farmers Market",
  "earnings": 20,
  "startingearnings": 20,
  "city": "Oakland",
  "amount": 6,
  "expire": 1,
  "items": {
    "grape": 3,
    "kiwi": 2,
    "orange": 1
  },
  "demand": 0,
  "generator": "equal_everything"
},
{
  "name": "Evelyn",
  "id": "order240",
  "store": "Safeway",
  "earnings": 20,
  "startingearnings": 20,
  "city": "Piedmont",
  "amount": 3,
  "expire": 1,
  "items": {
    "watermelon": 2,
    "apple": 1
  },
  "demand": 0,
  "generator": "pure_randomness"
},
{
  "name": "Matthew",
  "id": "order241",
  "store": "Berkeley Bowl",
  "earnings": 19,
  "startingearnings": 19,
  "city": "Berkeley",
  "amount": 10,
  "expire": 1,
  "items": {
    "watermelon": 3,
    "grape": 3,
    "pineapple": 1,
    "orange": 3
  },
  "demand": 0,
  "generator": "pure_randomness"
},
{
  "name": "Christopher",
  "id": "order242",
  "store": "Sprouts Farmers Market",
  "earnings": 25,
  "startingearnings": 25,
  "city": "Oakland",
  "amount": 18,
  "expire": 1,
  "items": {
    "watermelon": 3,
    "pear": 2,
    "kiwi": 3,
    "apple": 2,
    "grape": 5,
    "pineapple": 2,
    "orange": 1
  },
  "demand": 0,
  "generator": "pure_randomness"
},
{
  "name": "Ethan",
  "id": "order243",
  "store": "Safeway",
  "earnings": 9,
  "startingearnings": 9,
  "city": "Piedmont",
  "amount": 2,
  "expire": 1,
  "items": {
    "apple": 1,
    "watermelon": 1
  },
  "demand": 0,
  "generator": "pure_randomness"
},
{
  "name": "Olivia",
  "id": "order240",
  "store": "Sprouts Farmers Market",
  "earnings": 20,
  "startingearnings": 20,
  "city": "Oakland",
  "amount": 9,
  "expire": 1,
  "items": {
    "kiwi": 3,
    "apple": 2,
    "pear": 1,
    "grape": 1,
    "watermelon": 2
  },
  "demand": 0,
  "generator": "equal_location_earnings"
},
{
  "name": "Logan",
  "id": "order241",
  "store": "Sprouts Farmers Market",
  "earnings": 20,
  "startingearnings": 20,
  "city": "Oakland",
  "amount": 1,
  "expire": 1,
  "items": {
    "apple": 1
  },
  "demand": 0,
  "generator": "equal_location_earnings"
},
{
  "name": "Emma",
  "id": "order242",
  "store": "Sprouts Farmers Market",
  "earnings": 20,
  "startingearnings": 20,
  "city": "Oakland",
  "amount": 6,
  "expire": 1,
  "items": {
    "grape": 1,
    "apple": 1,
    "pineapple": 2,
    "watermelon": 1,
    "kiwi": 1
  },
  "demand": 0,
  "generator": "equal_location_earnings"
},
{
  "name": "Abigail",
  "id": "order243",
  "store": "Sprouts Farmers Market",
  "earnings": 20,
  "startingearnings": 20,
  "city": "Oakland",
  "amount": 11,
  "expire": 1,
  "items": {
    "pear": 2,
    "kiwi": 2,
    "watermelon": 2,
    "pineapple": 3,
    "grape": 1,
    "apple": 1
  },
  "demand": 0,
  "generator": "equal_location_earnings"
},
{
  "name": "Ethan",
  "id": "order244",
  "store": "Sprouts Farmers Market",
  "earnings": 20,
  "startingearnings": 20,
  "city": "Oakland",
  "amount": 15,
  "expire": 1,
  "items": {
    "apple": 4,
    "grape": 5,
    "watermelon": 3,
    "pineapple": 2,
    "pear": 1
  },
  "demand": 0,
  "generator": "commonsense_item_amount"
},
{
  "name": "Amelia",
  "id": "order245",
  "store": "Sprouts Farmers Market",
  "earnings": 20,
  "startingearnings": 20,
  "city": "Oakland",
  "amount": 15,
  "expire": 1,
  "items": {
    "orange": 5,
    "apple": 7,
    "watermelon": 1,
    "grape": 2
  },
  "demand": 0,
  "generator": "commonsense_item_amount"
},
{
  "name": "Liam",
  "id": "order246",
  "store": "Sprouts Farmers Market",
  "earnings": 20,
  "startingearnings": 20,
  "city": "Oakland",
  "amount": 15,
  "expire": 1,
  "items": {
    "apple": 4,
    "pear": 2,
    "pineapple": 3,
    "orange": 4,
    "kiwi": 2
  },
  "demand": 0,
  "generator": "commonsense_item_amount"
},
{
  "name": "Elijah",
  "id": "order247",
  "store": "Sprouts Farmers Market",
  "earnings": 20,
  "startingearnings": 20,
  "city": "Oakland",
  "amount": 5,
  "expire": 1,
  "items": {
    "orange": 5
  },
  "demand": 0,
  "generator": "commonsense_item_amount"
},
{
  "name": "Michael",
  "id": "order248",
  "store": "Sprouts Farmers Market",
  "earnings": 20,
  "startingearnings": 20,
  "city": "Oakland",
  "amount": 6,
  "expire": 1,
  "items": {
    "pineapple": 3,
    "pear": 1,
    "apple": 2
  },
  "demand": 0,
  "generator": "equal_everything"
},
{
  "name": "Liam",
  "id": "order249",
  "store": "Sprouts Farmers Market",
  "earnings": 20,
  "startingearnings": 20,
  "city": "Oakland",
  "amount": 6,
  "expire": 1,
  "items": {
    "pineapple": 3,
    "pear": 3
  },
  "demand": 0,
  "generator": "equal_everything"
},
{
  "name": "Amelia",
  "id": "order250",
  "store": "Sprouts Farmers Market",
  "earnings": 20,
  "startingearnings": 20,
  "city": "Oakland",
  "amount": 6,
  "expire": 1,
  "items": {
    "pear": 4,
    "grape": 2
  },
  "demand": 0,
  "generator": "equal_everything"
},
{
  "name": "Matthew",
  "id": "order251",
  "store": "Sprouts Farmers Market",
  "earnings": 20,
  "startingearnings": 20,
  "city": "Oakland",
  "amount": 6,
  "expire": 1,
  "items": {
    "pear": 2,
    "grape": 2,
    "watermelon": 2
  },
  "demand": 0,
  "generator": "equal_everything"
},
{
  "name": "James",
  "id": "order252",
  "store": "Sprouts Farmers Market",
  "earnings": 20,
  "startingearnings": 20,
  "city": "Oakland",
  "amount": 7,
  "expire": 1,
  "items": {
    "orange": 3,
    "apple": 1,
    "kiwi": 1,
    "pineapple": 2
  },
  "demand": 0,
  "generator": "equal_location_earnings"
},
{
  "name": "Joseph",
  "id": "order253",
  "store": "Sprouts Farmers Market",
  "earnings": 20,
  "startingearnings": 20,
  "city": "Oakland",
  "amount": 7,
  "expire": 1,
  "items": {
    "pear": 1,
    "watermelon": 1,
    "kiwi": 2,
    "orange": 1,
    "pineapple": 1,
    "apple": 1
  },
  "demand": 0,
  "generator": "equal_location_earnings"
},
{
  "name": "Ava",
  "id": "order254",
  "store": "Sprouts Farmers Market",
  "earnings": 20,
  "startingearnings": 20,
  "city": "Oakland",
  "amount": 16,
  "expire": 1,
  "items": {
    "pear": 4,
    "grape": 2,
    "kiwi": 2,
    "apple": 2,
    "watermelon": 2,
    "pineapple": 3,
    "orange": 1
  },
  "demand": 0,
  "generator": "equal_location_earnings"
},
{
  "name": "Ava",
  "id": "order255",
  "store": "Sprouts Farmers Market",
  "earnings": 20,
  "startingearnings": 20,
  "city": "Oakland",
  "amount": 18,
  "expire": 1,
  "items": {
    "kiwi": 2,
    "pineapple": 3,
    "grape": 3,
    "watermelon": 2,
    "pear": 5,
    "orange": 1,
    "apple": 2
  },
  "demand": 0,
  "generator": "equal_location_earnings"
},
{
  "name": "Elijah",
  "id": "order256",
  "store": "Safeway",
  "earnings": 36,
  "startingearnings": 36,
  "city": "Piedmont",
  "amount": 9,
  "expire": 1,
  "items": {
    "orange": 3,
    "apple": 5,
    "watermelon": 1
  },
  "demand": 0,
  "generator": "pure_randomness"
},
{
  "name": "Ethan",
  "id": "order257",
  "store": "Safeway",
  "earnings": 1,
  "startingearnings": 1,
  "city": "Piedmont",
  "amount": 18,
  "expire": 1,
  "items": {
    "watermelon": 9,
    "apple": 6,
    "orange": 3
  },
  "demand": 0,
  "generator": "pure_randomness"
},
{
  "name": "Olivia",
  "id": "order258",
  "store": "Berkeley Bowl",
  "earnings": 33,
  "startingearnings": 33,
  "city": "Berkeley",
  "amount": 5,
  "expire": 1,
  "items": {
    "orange": 1,
    "watermelon": 1,
    "grape": 2,
    "pineapple": 1
  },
  "demand": 0,
  "generator": "pure_randomness"
},
{
  "name": "Jacob",
  "id": "order259",
  "store": "Berkeley Bowl",
  "earnings": 13,
  "startingearnings": 13,
  "city": "Berkeley",
  "amount": 11,
  "expire": 1,
  "items": {
    "watermelon": 1,
    "grape": 3,
    "pineapple": 3,
    "apple": 3,
    "orange": 1
  },
  "demand": 0,
  "generator": "pure_randomness"
},
{
  "name": "Michael",
  "id": "order256",
  "store": "Sprouts Farmers Market",
  "earnings": 20,
  "startingearnings": 20,
  "city": "Oakland",
  "amount": 6,
  "expire": 1,
  "items": {
    "kiwi": 3,
    "pineapple": 2,
    "watermelon": 1
  },
  "demand": 0,
  "generator": "equal_everything"
},
{
  "name": "Olivia",
  "id": "order257",
  "store": "Sprouts Farmers Market",
  "earnings": 20,
  "startingearnings": 20,
  "city": "Oakland",
  "amount": 6,
  "expire": 1,
  "items": {
    "kiwi": 2,
    "apple": 4
  },
  "demand": 0,
  "generator": "equal_everything"
},
{
  "name": "Emma",
  "id": "order258",
  "store": "Sprouts Farmers Market",
  "earnings": 20,
  "startingearnings": 20,
  "city": "Oakland",
  "amount": 6,
  "expire": 1,
  "items": {
    "watermelon": 3,
    "kiwi": 1,
    "apple": 2
  },
  "demand": 0,
  "generator": "equal_everything"
},
{
  "name": "Aiden",
  "id": "order259",
  "store": "Sprouts Farmers Market",
  "earnings": 20,
  "startingearnings": 20,
  "city": "Oakland",
  "amount": 6,
  "expire": 1,
  "items": {
    "orange": 3,
    "watermelon": 2,
    "pear": 1
  },
  "demand": 0,
  "generator": "equal_everything"
}
]